Khizar/cnn_using_verilog/renzym-design/hw/rtl/max_pool.v
//////////////////////////////////////////////////////////////////////////////////
// Company: 		Renzym
// Engineer: 		Yasir Javed
// Design Name: 	max_pool
// Module Name:		Max Pool
// Description: 	One dimentional Maxpool between two values, can be enabled/disabled
//
//					
// Dependencies:	 
//
//////////////////////////////////////////////////////////////////////////////////
module max_pool
	#(
		parameter DWIDTH = 8
	)
	(
	input						clk,
	input						reset,
	input						en_maxpool,
	input		[DWIDTH-1:0]	data_in,
	input						valid_in,
	
	output reg	[DWIDTH-1:0]	data_out,
	output reg					valid_out
	);

	reg	[DWIDTH-1:0]	data_r;
	reg	[DWIDTH-1:0]	data_r_r;
	reg	[DWIDTH-1:0]	max_pool_out;
	reg					max_pool_valid;

	always@(posedge clk)
		if(reset)			data_r		<= 0;
		else if(valid_in)	data_r		<= data_in;

	always@* max_pool_out <= (data_r > data_in) ? data_r: data_in;
	

	reg toggle;	
	always@(posedge clk)
		if		(reset | ~en_maxpool)	toggle <= 0;
		else if (valid_in)				toggle <= ~toggle;
	
	always@* max_pool_valid <= toggle & valid_in;

	always@(posedge clk) 
		if(reset)	
		begin
			data_out 	<= 0;
		    valid_out	<= 0;
		end
		else
		begin
			data_out 	<= en_maxpool ? max_pool_out	: data_in;
		    valid_out	<= en_maxpool ? max_pool_valid	: valid_in;
		end

endmodule

Khizar/cnn_using_verilog/renzym-design/hw/sim/tb_maxpool.v
module tb_maxpool;
	parameter DWIDTH = 8;
	reg						clk;
	reg						reset;
	reg						en_maxpool;
	reg		[DWIDTH-1:0]	data_in;
	reg						valid_in;
	
	wire 	[DWIDTH-1:0]	data_out;
	wire					valid_out;
	integer					i;
	max_pool
	#(
		.DWIDTH 	(8			)
	)
	max_pool_inst
	(
	.clk			(clk		),
	.reset			(reset		),
	.en_maxpool		(en_maxpool	),
	.data_in		(data_in	),
	.valid_in		(valid_in	),
	.data_out		(data_out	),
	.valid_out		(valid_out	)
	);
	
	initial
	begin
		clk = 0;
		forever #5 clk = ~clk;
	end

	initial
	begin
		$dumpfile("wave_mp.vcd");
		$dumpvars(0, tb_maxpool);
		
		reset		= 0;
		en_maxpool	= 0;
		data_in		= 0;
		valid_in	= 0;

		repeat(2) @(posedge clk);
		#1 reset		= 1;

		repeat(2) @(posedge clk);
		#1 reset		= 0;
		
		repeat(10) @(posedge clk);
		
		#1 valid_in = 1;
		for(i=1; i <20; i=i+1)
		begin
			@(posedge clk);
			#1 data_in = i;
		end
		#1 valid_in = 0;
					
		repeat(10) @(posedge clk);
		#1 valid_in = 1;
		data_in		= 0;
		en_maxpool	= 1;
		for(i=1; i <20; i=i+1)
		begin
			@(posedge clk);
			#1 data_in = i;
		end
		
		$finish;
	end

endmodule

Khizar/cnn_using_verilog/renzym-design/hw/sim/wave_mp.vcd
$date
	Tue Jun 15 13:11:34 2021
$end
$version
	Icarus Verilog
$end
$timescale
	1s
$end
$scope module tb_maxpool $end
$var wire 1 ! valid_out $end
$var wire 8 " data_out [7:0] $end
$var reg 1 # clk $end
$var reg 8 $ data_in [7:0] $end
$var reg 1 % en_maxpool $end
$var reg 1 & reset $end
$var reg 1 ' valid_in $end
$var integer 32 ( i [31:0] $end
$scope module max_pool_inst $end
$var wire 1 # clk $end
$var wire 8 ) data_in [7:0] $end
$var wire 1 % en_maxpool $end
$var wire 1 & reset $end
$var wire 1 ' valid_in $end
$var reg 8 * data_out [7:0] $end
$var reg 8 + data_r [7:0] $end
$var reg 8 , max_pool_out [7:0] $end
$var reg 1 - max_pool_valid $end
$var reg 1 . toggle $end
$var reg 1 ! valid_out $end
$upscope $end
$upscope $end
$enddefinitions $end
#0
$dumpvars
x.
x-
bx ,
bx +
b0 *
b0 )
bx (
0'
0&
0%
b0 $
0#
b0 "
0!
$end
#5
0.
0-
1#
#10
0#
#15
1#
#16
1&
#20
0#
#25
b0 +
b0 ,
1#
#30
0#
#35
1#
#36
0&
#40
0#
#45
1#
#50
0#
#55
1#
#60
0#
#65
1#
#70
0#
#75
1#
#80
0#
#85
1#
#90
0#
#95
1#
#100
0#
#105
1#
#110
0#
#115
1#
#120
0#
#125
1#
#130
0#
#135
1#
#136
1!
b1 (
1'
#140
0#
#145
1#
#146
b1 "
b1 *
b10 (
b1 $
b1 )
#150
0#
#155
b1 ,
b1 +
1#
#156
b10 "
b10 *
b11 (
b10 $
b10 )
#160
0#
#165
b10 +
b10 ,
1#
#166
b11 "
b11 *
b100 (
b11 $
b11 )
#170
0#
#175
b11 ,
b11 +
1#
#176
b100 "
b100 *
b101 (
b100 $
b100 )
#180
0#
#185
b100 +
b100 ,
1#
#186
b101 "
b101 *
b110 (
b101 $
b101 )
#190
0#
#195
b101 ,
b101 +
1#
#196
b110 "
b110 *
b111 (
b110 $
b110 )
#200
0#
#205
b110 +
b110 ,
1#
#206
b111 "
b111 *
b1000 (
b111 $
b111 )
#210
0#
#215
b111 ,
b111 +
1#
#216
b1000 "
b1000 *
b1001 (
b1000 $
b1000 )
#220
0#
#225
b1000 +
b1000 ,
1#
#226
b1001 "
b1001 *
b1010 (
b1001 $
b1001 )
#230
0#
#235
b1001 ,
b1001 +
1#
#236
b1010 "
b1010 *
b1011 (
b1010 $
b1010 )
#240
0#
#245
b1010 +
b1010 ,
1#
#246
b1011 "
b1011 *
b1100 (
b1011 $
b1011 )
#250
0#
#255
b1011 ,
b1011 +
1#
#256
b1100 "
b1100 *
b1101 (
b1100 $
b1100 )
#260
0#
#265
b1100 +
b1100 ,
1#
#266
b1101 "
b1101 *
b1110 (
b1101 $
b1101 )
#270
0#
#275
b1101 ,
b1101 +
1#
#276
b1110 "
b1110 *
b1111 (
b1110 $
b1110 )
#280
0#
#285
b1110 +
b1110 ,
1#
#286
b1111 "
b1111 *
b10000 (
b1111 $
b1111 )
#290
0#
#295
b1111 ,
b1111 +
1#
#296
b10000 "
b10000 *
b10001 (
b10000 $
b10000 )
#300
0#
#305
b10000 +
b10000 ,
1#
#306
b10001 "
b10001 *
b10010 (
b10001 $
b10001 )
#310
0#
#315
b10001 ,
b10001 +
1#
#316
b10010 "
b10010 *
b10011 (
b10010 $
b10010 )
#320
0#
#325
b10010 +
b10010 ,
1#
#326
b10011 "
b10011 *
b10100 (
b10011 $
b10011 )
#327
0!
0'
#330
0#
#335
b10011 ,
1#
#340
0#
#345
1#
#350
0#
#355
1#
#360
0#
#365
1#
#370
0#
#375
1#
#380
0#
#385
1#
#390
0#
#395
1#
#400
0#
#405
1#
#410
0#
#415
1#
#420
0#
#425
1#
#426
b1 (
1%
b0 $
b0 )
1'
#430
0#
#435
b10010 "
b10010 *
1.
b10010 ,
b0 +
1#
#436
b10 (
b1 $
b1 )
#440
0#
#445
b1 "
b1 *
1!
b1 +
b1 ,
0.
1-
1#
#446
b11 (
b10 $
b10 )
#450
0#
#455
0!
b10 "
b10 *
0-
1.
b10 ,
b10 +
1#
#456
b100 (
b11 $
b11 )
#460
0#
#465
b11 "
b11 *
1!
b11 +
b11 ,
0.
1-
1#
#466
b101 (
b100 $
b100 )
#470
0#
#475
0!
b100 "
b100 *
0-
1.
b100 ,
b100 +
1#
#476
b110 (
b101 $
b101 )
#480
0#
#485
b101 "
b101 *
1!
b101 +
b101 ,
0.
1-
1#
#486
b111 (
b110 $
b110 )
#490
0#
#495
0!
b110 "
b110 *
0-
1.
b110 ,
b110 +
1#
#496
b1000 (
b111 $
b111 )
#500
0#
#505
b111 "
b111 *
1!
b111 +
b111 ,
0.
1-
1#
#506
b1001 (
b1000 $
b1000 )
#510
0#
#515
0!
b1000 "
b1000 *
0-
1.
b1000 ,
b1000 +
1#
#516
b1010 (
b1001 $
b1001 )
#520
0#
#525
b1001 "
b1001 *
1!
b1001 +
b1001 ,
0.
1-
1#
#526
b1011 (
b1010 $
b1010 )
#530
0#
#535
0!
b1010 "
b1010 *
0-
1.
b1010 ,
b1010 +
1#
#536
b1100 (
b1011 $
b1011 )
#540
0#
#545
b1011 "
b1011 *
1!
b1011 +
b1011 ,
0.
1-
1#
#546
b1101 (
b1100 $
b1100 )
#550
0#
#555
0!
b1100 "
b1100 *
0-
1.
b1100 ,
b1100 +
1#
#556
b1110 (
b1101 $
b1101 )
#560
0#
#565
b1101 "
b1101 *
1!
b1101 +
b1101 ,
0.
1-
1#
#566
b1111 (
b1110 $
b1110 )
#570
0#
#575
0!
b1110 "
b1110 *
0-
1.
b1110 ,
b1110 +
1#
#576
b10000 (
b1111 $
b1111 )
#580
0#
#585
b1111 "
b1111 *
1!
b1111 +
b1111 ,
0.
1-
1#
#586
b10001 (
b10000 $
b10000 )
#590
0#
#595
0!
b10000 "
b10000 *
0-
1.
b10000 ,
b10000 +
1#
#596
b10010 (
b10001 $
b10001 )
#600
0#
#605
b10001 "
b10001 *
1!
b10001 +
b10001 ,
0.
1-
1#
#606
b10011 (
b10010 $
b10010 )
#610
0#
#615
0!
b10010 "
b10010 *
0-
1.
b10010 ,
b10010 +
1#
#616
b10100 (
b10011 $
b10011 )
