Khizar/pipeline/registerfilenew.v
module registerfilenew(clk, rs1, rs2, rd, writedata, regwrite, readdata1, readdata2);

    input clk;
    input [4:0] rs1, rs2, rd;
    input [31:0] writedata;
    input regwrite;

    output wire [31:0] readdata1, readdata2;

    reg [31:0] regfile [0:31];

    initial 
    begin
      regfile[0] <= 0;
    end

    wire x1 = (rd == rs1 & rd != 0 & regwrite == 1);
    wire x2 = (rd == rs2 & rd != 0 & regwrite == 1);
    assign readdata1 =  x1 ? writedata: regfile[rs1];
    assign readdata2 =  x2 ? writedata: regfile[rs2];

    always @ (posedge clk)
    begin
        if (regwrite == 1 & rd != 0)
          regfile[rd] <= writedata;

    end

endmodule

Khizar/pipeline/registerfilenew_tb.v
`include "registerfilenew.v"

module registerfile_tb;

    reg clk;
    reg [4:0] rs1, rs2, rd;
    reg [31:0] writedata;
    reg regwrite;
    wire [31:0] readdata1, readdata2;

    //rs1, rs2, rd, writedata, regwrite, readdata1, readdata2
    registerfilenew uut(clk, rs1, rs2, rd, writedata, regwrite, readdata1, readdata2);

    always #1 clk = ~clk;

    //initialize some registers
    initial
        begin
            $dumpfile("../vcd/registerfile_tb.vcd");
            $dumpvars(3, registerfile_tb);

            clk = 0;
            rs1 = 0;
            rs2 = 0;
            rd  = 0;
            writedata = 0;
            regwrite = 0;

            #3
            regwrite = 1;

            #3 // x0 = 0
            rd            = 5'b00000;
            writedata     = {{28{1'b0}}, 4'b0000};

            #3 // x1 = 1
            rd            = 5'b00001;
            writedata     = {{28{1'b0}}, 4'b0001};

            #3 // x2 = 2
            rd            = 5'b00010;
            writedata     = {{28{1'b0}}, 4'b0010};

            #3 // x3 = 3
            rd            = 5'b00011;
            writedata     = {{28{1'b0}}, 4'b0011};

            #3 // x4 = 4
            rd            = 5'b00100;
            writedata     = {{28{1'b0}}, 4'b0100};
            
            #3 // x5 = 5
            rd            = 5'b00101;
            writedata     = {{28{1'b0}}, 4'b0101};
            
            #3
            rs1           = 5'b00000;
            rs2           = 5'b00001;

            #3
            $display("x0...: %d", readdata1);
            $display("x1: %d", readdata2);

            #3
            rs1           = 5'b00010;
            rs2           = 5'b00011;

            #3
            $display("x2: %d", readdata1);
            $display("x3: %d", readdata2);

            #3
            rs1           = 5'b00100;
            rs2           = 5'b00101;

            #3
            $display("x4: %d", readdata1);
            $display("x5: %d", readdata2);

            #3
            rs1           = 5'b00010;
            rs2           = 5'b00100;

            #3
            $display("x2: %d", readdata1);
            $display("x4: %d", readdata2);

            #3
            regwrite = 0;
            rd            = 5'b00001;
            writedata     = {{28{1'b0}}, 4'b0100};

            #3 // x0 = 0
            rd            = 5'b00011;
            writedata     = {{28{1'b0}}, 4'b0110};

            #3
            rs1           = 5'b00001;
            rs2           = 5'b00011;

            #3
            $display("x1: %d", readdata1);
            $display("x3: %d", readdata2);

            #3
            regwrite = 1;
            rs2           = 5'b00011;
            rd            = 5'b00011;
            writedata     = {{28{1'b0}}, 4'b0111};
            rs1           = 5'b00001;
            $display("...rs1 (x1): %d", readdata1);
            $display("...rs2 (x3): %d", readdata2);

            #300 $finish;

        end



endmodule

Khizar/vcd/registerfile_tb.vcd
$date
	Fri Aug  4 18:48:48 2023
$end
$version
	Icarus Verilog
$end
$timescale
	1s
$end
$scope module registerfile_tb $end
$var wire 32 ! readdata2 [31:0] $end
$var wire 32 " readdata1 [31:0] $end
$var reg 1 # clk $end
$var reg 5 $ rd [4:0] $end
$var reg 1 % regwrite $end
$var reg 5 & rs1 [4:0] $end
$var reg 5 ' rs2 [4:0] $end
$var reg 32 ( writedata [31:0] $end
$scope module uut $end
$var wire 1 # clk $end
$var wire 5 ) rd [4:0] $end
$var wire 1 % regwrite $end
$var wire 5 * rs1 [4:0] $end
$var wire 5 + rs2 [4:0] $end
$var wire 32 , writedata [31:0] $end
$var wire 1 - x1 $end
$var wire 1 . x2 $end
$var wire 32 / readdata2 [31:0] $end
$var wire 32 0 readdata1 [31:0] $end
$upscope $end
$upscope $end
$enddefinitions $end
$comment Show the parameter values. $end
$dumpall
$end
#0
$dumpvars
b0 0
b0 /
0.
0-
b0 ,
b0 +
b0 *
b0 )
b0 (
b0 '
b0 &
0%
b0 $
0#
b0 "
b0 !
$end
#1
1#
#2
0#
#3
1#
1%
#4
0#
#5
1#
#6
0#
#7
1#
#8
0#
#9
1#
b1 (
b1 ,
b1 $
b1 )
#10
0#
#11
1#
#12
0#
b10 (
b10 ,
b10 $
b10 )
#13
1#
#14
0#
#15
1#
b11 (
b11 ,
b11 $
b11 )
#16
0#
#17
1#
#18
0#
b100 (
b100 ,
b100 $
b100 )
#19
1#
#20
0#
#21
1#
b101 (
b101 ,
b101 $
b101 )
#22
0#
#23
1#
#24
b1 !
b1 /
0#
b1 '
b1 +
#25
1#
#26
0#
#27
1#
#28
0#
#29
1#
#30
b11 !
b11 /
b10 "
b10 0
0#
b11 '
b11 +
b10 &
b10 *
#31
1#
#32
0#
#33
1#
#34
0#
#35
1#
#36
1.
b101 !
b101 /
b100 "
b100 0
0#
b101 '
b101 +
b100 &
b100 *
#37
1#
#38
0#
#39
1#
#40
0#
#41
1#
#42
b100 !
b100 /
0.
b10 "
b10 0
0#
b100 '
b100 +
b10 &
b10 *
#43
1#
#44
0#
#45
1#
#46
0#
#47
1#
#48
0#
b100 (
b100 ,
b1 $
b1 )
0%
#49
1#
#50
0#
#51
1#
b110 (
b110 ,
b11 $
b11 )
#52
0#
#53
1#
#54
b11 !
b11 /
b1 "
b1 0
0#
b11 '
b11 +
b1 &
b1 *
#55
1#
#56
0#
#57
1#
#58
0#
#59
1#
#60
b111 !
b111 /
1.
0#
b111 (
b111 ,
1%
