Khizar/verilog/single-cycle/old/alucontrol.v
module alucontrol(aluop, func7, func3, aluctl);

    input [1:0] aluop;
    input [6:0] func7;
    input [2:0] func3;

    output reg [3:0] aluctl;

    always @ (aluop, func7, func3)
        begin
          if (aluop == 2'b00)
            aluctl <= 4'b0010;
          else if (aluop == 2'b01) 
            aluctl <= 4'b0110;
          else if (aluop == 2'b10)
            begin
              if (func7 == 7'b0000000)
                begin
                  if (func3 == 3'b000)
                    aluctl <= 4'b0010;
                  else if (func3 == 3'b111)
                    aluctl <= 4'b0000;
                  else if (func3 == 3'b100)
                    aluctl <= 4'b1100;
                  else if (func3 == 3'b110)
                    aluctl <= 4'b0001;
                end
              else if (func7 == 7'b0100000)
                begin
                  if (func3 == 3'b000)
                    aluctl <= 4'b0110;
                end
            end
        end

endmodule

Khizar/verilog/single-cycle/withclock/alucontrol_tb.v
`include "alucontrol.v"

module alucontrol_tb;//(aluop, func7, func3, aluctl);

    reg [1:0] aluop;
    reg [6:0] func7;
    reg [2:0] func3;

    wire [3:0] aluctl;

    alucontrol uut(aluop, func7, func3, aluctl);

    initial 
        begin
            $dumpfile("./vcd/alucontrol_tb.vcd");
            $dumpvars(1, alucontrol_tb);

            #1
            aluop = 2'b00;
            func7 = 7'b000_0000;
            func3 = 3'b000;

            #1
            $display("aluctl: %d", aluctl);

            #1
            aluop = 2'b00;
            func7 = 7'b000_1111;
            func3 = 3'b010;

            #1
            $display("aluctl: %d", aluctl);

            #1
            aluop = 2'b00;
            func7 = 7'b111_1001;
            func3 = 3'b111;

            #1
            $display("aluctl: %d", aluctl);

            #1
            aluop = 2'b01;
            func7 = 7'b000_1001;
            func3 = 3'b111;

            #1
            $display("aluctl: %d", aluctl);

            #1
            aluop = 2'b01;
            func7 = 7'b111_1101;
            func3 = 3'b001;

            #1
            $display("aluctl: %d", aluctl);

            #1
            aluop = 2'b01;
            func7 = 7'b001_1111;
            func3 = 3'b101;

            #1
            $display("aluctl: %d", aluctl);

            #1
            aluop = 2'b10;
            func7 = 7'b000_0000;
            func3 = 3'b000;

            #1
            $display("aluctl: %d", aluctl);

            #1
            aluop = 2'b10;
            func7 = 7'b010_0000;
            func3 = 3'b000;

            #1
            $display("aluctl: %d", aluctl);

            #1
            aluop = 2'b10;
            func7 = 7'b000_0000;
            func3 = 3'b111;

            #1
            $display("aluctl: %d", aluctl);

            #1
            aluop = 2'b10;
            func7 = 7'b000_0000;
            func3 = 3'b110;

            #1
            $display("aluctl: %d", aluctl);


        end

endmodule

Khizar/verilog/single-cycle/vcd/alucontrol_tb.vcd
$date
	Sat Jul 15 16:18:24 2023
$end
$version
	Icarus Verilog
$end
$timescale
	1s
$end
$scope module alucontrol_tb $end
$var wire 4 ! aluctl [3:0] $end
$var reg 2 " aluop [1:0] $end
$var reg 3 # func3 [2:0] $end
$var reg 7 $ func7 [6:0] $end
$upscope $end
$enddefinitions $end
#0
$dumpvars
bx $
bx #
bx "
bx !
$end
#1
b10 !
b0 #
b0 $
b0 "
#3
b10 #
b1111 $
#5
b111 #
b1111001 $
#7
b110 !
b1001 $
b1 "
#9
b1 #
b1111101 $
#11
b101 #
b11111 $
#13
b10 !
b0 #
b0 $
b10 "
#15
b110 !
b100000 $
#17
b0 !
b111 #
b0 $
#19
b1 !
b110 #
