Khizar/verilog/single-cycle/onlyclock/mux2_1.v
module mux2_1(in1, in2, s, out);

    input [31:0] in1, in2;
    input s;

    output reg [31:0] out;

    always @ (in1, in2, s)
        begin
            if (s == 0)
                out <= in1;
            else
                out <= in2;
        end

endmodule

Khizar/verilog/single-cycle/onlyclock/datamemory.v
module datamemory(clk, address, writedata, memread, memwrite, readdata);

    input clk;
    input memread, memwrite;
    input [31:0] writedata;
    input [9:0] address; // change later
    
    output wire [31:0] readdata;

    reg [7:0] memfile [0:1023]; // increase memory size later

    assign readdata = (memread == 1) ? {memfile[address+3], memfile[address+2], memfile[address+1], memfile[address]} : 0;

    always @ (posedge clk)
        begin
            if (memwrite == 1)
                {memfile[address+3], memfile[address+2], memfile[address+1], memfile[address]} <= writedata;
        end

endmodule

Khizar/verilog/singleImplem/alu.v
module alu(aluctl, a, b, out, zero, overflow);

    input [3:0] aluctl; 

    input [31:0] a;
    input [31:0] b;

    output reg [31:0] out;
    output zero, overflow;

    assign zero = (out == 0);

    always @ (aluctl, a, b)
        begin
            case (aluctl)
                0: out <= a & b;
                1: out <= a | b;
                2: out <= a + b;
                6: out <= a - b;
                7: out <= (a < b ? 1: 0);
                12: out <= ~(a | b);
                default: out <= 0;
            endcase
        end

endmodule

Khizar/verilog/single-cycle/old/alucontrol.v
module alucontrol(aluop, func7, func3, aluctl);

    input [1:0] aluop;
    input [6:0] func7;
    input [2:0] func3;

    output reg [3:0] aluctl;

    always @ (aluop, func7, func3)
        begin
          if (aluop == 2'b00)
            aluctl <= 4'b0010;
          else if (aluop == 2'b01) 
            aluctl <= 4'b0110;
          else if (aluop == 2'b10)
            begin
              if (func7 == 7'b0000000)
                begin
                  if (func3 == 3'b000)
                    aluctl <= 4'b0010;
                  else if (func3 == 3'b111)
                    aluctl <= 4'b0000;
                  else if (func3 == 3'b100)
                    aluctl <= 4'b1100;
                  else if (func3 == 3'b110)
                    aluctl <= 4'b0001;
                end
              else if (func7 == 7'b0100000)
                begin
                  if (func3 == 3'b000)
                    aluctl <= 4'b0110;
                end
            end
        end

endmodule

Khizar/verilog/single-cycle/riscv-single-cycle/immediategen.v
module immediategen(instruction, result);

    //opcode types
    localparam I = 7'b0010011;
    localparam S = 7'b0100011;
    localparam SB = 7'b1100011;
    localparam I_LD = 7'b0000011;

    input [31:0] instruction;

    output reg [31:0] result;

    always @ (instruction)
        begin
            case (instruction[6:0])
                I_LD, I: 
                    result <= {{20{instruction[31]}}, instruction[31:20]};
                S: 
                    result <= {{19{instruction[31]}}, instruction[31:25], instruction[11:7]};
                SB: 
                    result <= {{18{instruction[31]}}, instruction[31], instruction[7], instruction[30:25], instruction[11:8], 1'b0};
                    
                default: result <= 0;
            endcase
        end

endmodule

Khizar/verilog/single-cycle/onlyclock/registerfile.v
module registerfile(clk, rs1, rs2, rd, writedata, regwrite, readdata1, readdata2);

    input clk;
    input [4:0] rs1, rs2, rd;
    input [31:0] writedata;
    input regwrite;

    output reg [31:0] readdata1, readdata2;

    reg [31:0] regfile [0:31];

    
    
    always @ (posedge clk)
        begin
          if (regwrite == 1)
            begin
              regfile[rd] <= writedata;
            end

          regfile[0] <= 0;

          readdata1 <= regfile[rs1];
          readdata2 <= regfile[rs2];
        end

endmodule

Khizar/verilog/single-cycle/riscv-single-cycle/maincontrol.v
module maincontrol(clk, instruction, branch, memread, memtoreg, aluop, memwrite, alusrc, regwrite);

  //opcode types
  localparam I = 7'b0010011;
  localparam S = 7'b0100011;
  localparam SB = 7'b1100011;
  localparam I_LD = 7'b0000011;

  input clk;
  input [6:0] instruction;

  output reg branch, memread, memtoreg, memwrite, alusrc, regwrite;
  output reg [1:0] aluop;

  always @ (instruction)
    begin
      case (instruction)
        7'b0110011:
          {aluop, alusrc, memtoreg, regwrite, memread, memwrite, branch} = 8'b10_0_0_1_0_0_0;
        7'b0000011:
          {aluop, alusrc, memtoreg, regwrite, memread, memwrite, branch} = 8'b00_1_1_1_1_0_0;
        7'b0100011:
          {aluop, alusrc, memtoreg, regwrite, memread, memwrite, branch} = 8'b00_1_0_0_0_1_0;
        7'b1100011:
          {aluop, alusrc, memtoreg, regwrite, memread, memwrite, branch} = 8'b01_0_0_0_0_0_1;
        7'b0010011: // for addi (i-type)
          {aluop, alusrc, memtoreg, regwrite, memread, memwrite, branch} = 8'b00_1_0_1_0_0_0;
        default:
          {aluop, alusrc, memtoreg, regwrite, memread, memwrite, branch} = 8'b00_0_0_0_0_0_0;
      endcase
    end

endmodule

Khizar/verilog/single-cycle/onlyclock/instructionmemory.v
module instructionmemory(clk, pc, instruction);

    input clk;
    input [9:0] pc; // change later
    
    output reg [31:0] instruction;

    reg [31:0] memfile [0:1023]; // increase memory size later

    initial
        begin // write instructions here
            // x0 = 0 already done

            //  addi x10, x0,  1     
            memfile[0] <= 32'b0000_0000_0001___00000___000___01010___001_0011;          //  x10     =   1

            //  addi x11, x10, 1
            memfile[1] <= 32'b0000_0000_0001___01010___000___01011___001_0011;          //  x11     =   2

            //  addi x12, x10, 2
            memfile[2] <= 32'b0000_0000_0010___01010___000___01100___001_0011;          //  x12     =   3
            
            //  nop
            memfile[3] <= 32'b0000_0000_0000___00000___000___00000___000_0000;          //  nop
            
            //  sw   x10, 9(x0)
            memfile[4]  <= 32'b0000000___01010___00000___010___01001___010_0011;        //  mem[9]  =   1

            //  nop
            memfile[5] <= 32'b0000_0000_0000___00000___000___00000___000_0000;          //  nop
            
            //  addi x13, x10, 3 
            memfile[6] <= 32'b0000_0000_0011___01010___000___01101___001_0011;          //  x13     =   4

            //  add  x14, x11, x13                                                                                               
            memfile[7] <= 32'b0000000___01011___01101___000___01110___011_0011;         //  x14     =   6   (x14 = x11 + x13)

            //  addi x15, x14, 0
            memfile[8] <= 32'b0000_0000_0000___01110___000___01111___001_0011;          //  x15     =   6   (x15 = x14 + 0)

            //  sub x16, x15, x11
            memfile[9] <= 32'b0100000___01011___01111___000___10000___011_0011;          // x16     =   4   (x16 = x15 - x11)
                
            //  addi x17, x16, 0
            memfile[10] <= 32'b0000_0000_0000___10000___000___10001___001_0011;          //  x17     =   4   (x17 = x16 + 0)

            //  sw   x11, 4(x0)         
            memfile[11]  <= 32'b0000000___01011___00000___010___00100___010_0011;         //  mem[4]  =   2

            //  nop
            memfile[12] <= 32'b0000_0000_0000___00000___000___00000___000_0000;         //  nop

            //  sw   x12, 5(x0)         
            memfile[13] <= 32'b0000000___01100___00000___010___00101___010_0011;         // mem[5]  =   3

            //  nop
            memfile[14] <= 32'b0000_0000_0000___00000___000___00000___000_0000;         //  nop

            //  lw   x18, 5(x0)         
            memfile[15] <= 32'b0000_0000_0101___00000___010___10010___000_0011;         //  x18     =   mem[5]  =   3
            
            //  nop
            memfile[16] <= 32'b0000_0000_0000___00000___000___00000___000_0000;         //  nop

            //  addi x19, x18, 0
            memfile[17] <= 32'b0000_0000_0000___10010___000___10011___001_0011;          //  x19     =   3   (x19 = x18 + 0)

            //  and  x20, x10, x18                                                                                               
            memfile[18] <= 32'b0000000___01010___10010___111___10100___011_0011;         //  x20     =   1   (x20 = x10 & x18)
            //  x10 = 0000_0000_0000_0000_0000_0000_0000_0001
            //  x18 = 0000_0000_0000_0000_0000_0000_0000_0011
            //  x20 = 0000_0000_0000_0000_0000_0000_0000_0001

            //  addi x23, x20, 0
            memfile[19] <= 32'b0000_0000_0000___10100___000___10111___001_0011;          //  x23     =   1   (x23 = x20 + 0)

            //  or  x21, x11, x16                                                                                               
            memfile[20] <= 32'b0000000___01011___10000___110___10101___011_0011;         //  x21     =   6   (x21 = x11 | x16)
            //  x11 = 0000_0000_0000_0000_0000_0000_0000_0010
            //  x16 = 0000_0000_0000_0000_0000_0000_0000_0100
            //  x21 = 0000_0000_0000_0000_0000_0000_0000_0110

            //  addi x24, x21, 0
            memfile[21] <= 32'b0000_0000_0000___10101___000___11000___001_0011;          //  x24     =   6   (x24 = x21 + 0)

            // xor  x22, x14, x17                                                                                               
            memfile[22] <= 32'b0000000___01110___10001___100___10110___011_0011;         //  x22     =   2   (x22 = x14 xor x17)
            //  x14 = 0000_0000_0000_0000_0000_0000_0000_0110
            //  x17 = 0000_0000_0000_0000_0000_0000_0000_0100
            //  x22 = 0000_0000_0000_0000_0000_0000_0000_0010

            //  addi x25, x22, 0
            memfile[23] <= 32'b0000_0000_0000___10110___000___11001___001_0011;          //  x25     =   2   (x25 = x22 + 0)

            //  nop
            memfile[24] <= 32'b0000_0000_0000___00000___000___00000___000_0000;         //  nop
            
            //  lw   x26, 4(x0)         
            memfile[25] <= 32'b0000_0000_0100___00000___010___11010___000_0011;         //  x26     =   mem[4]  = 2
                
            //  addi x27, x26, 0
            memfile[26] <= 32'b0000_0000_0000___11010___000___11011___001_0011;          //  x27     =   2   (x27 = x26 + 0)

            //  nop
            memfile[27] <= 32'b0000_0000_0000___00000___000___00000___000_0000;         //  nop

            //  lw   x30, 9(x0)         
            memfile[28] <= 32'b0000_0000_1001___00000___010___11110___000_0011;         //  x30     =   mem[9]  =   1
            //  nop
            memfile[29] <= 32'b0000_0000_0000___00000___000___00000___000_0000;         //  nop

            //  addi x31, x30, 0
            memfile[30] <= 32'b0000_0000_0000___11110___000___11111___001_0011;         //  x31     =   1
        end

    always @ (posedge clk)
        begin
            instruction <= memfile[pc];
        end

endmodule

Khizar/verilog/single-cycle/onlyclock/combined_tb.v
`include "maincontrol.v"
`include "alucontrol.v"
`include "alu.v"
`include "registerfile.v"
`include "instructionmemory.v"
`include "adder.v"
`include "datamemory.v"
`include "immediategen.v"
`include "mux2_1.v"

module combined_tb;

    reg [9:0] pc;
    reg clk;
    
    wire branch, memread, memtoreg, memwrite, alusrc, regwrite, zero;
    wire [1:0] aluop;
    wire [3:0] aluctl;
    wire [31:0] instruction, a, b, immediate, mux_out, alu_out, writedata, readdata, sumA, sumB;

    instructionmemory   uutA(clk, pc, instruction);
    maincontrol         uutB(clk, instruction[6:0], branch, memread, memtoreg, aluop, memwrite, alusrc, regwrite);
    registerfile        uutF(clk, instruction[19:15], instruction[24:20], instruction[11:7], writedata, regwrite, a, b);
    immediategen        uutD(instruction, immediate);
    alucontrol          uutC(aluop, instruction[31:25], instruction[14:12], aluctl);                   
    mux2_1              uutE(b, immediate, alusrc, mux_out);
    alu                 uutG(aluctl, a, mux_out, alu_out, zero, overflow);
    datamemory          uutH(clk, alu_out[9:0], b, memread, memwrite, readdata); // decreased address to 10 bits, change later
    mux2_1              uutI(alu_out, readdata, memtoreg, writedata);

    //adder               uutJ(pc, 4, pc);
    // adder               uutK(immediate, pc, sumB);
    // mux2_1              uutL(sumA, sumB, select, pc);

    integer i;

    always #1 clk = ~clk;

    initial
        begin
            $dumpfile("../vcd/combined_tb_clock.vcd");
            $dumpvars(2, combined_tb);

            pc = 0;
            clk = 0;

            for(i = 0; i < 32; i = i + 1)
                begin
                    #5
                    $display("ins: %d", instruction);
                    $display("branch %d, memread %d, memtoreg %d, aluop %d, memwrite %d, alusrc %d, regwrite %d", branch, memread, memtoreg, aluop, memwrite, alusrc, regwrite);
                    $display("alu_ctl %d, writedata %d, a %d, b %",  aluctl, writedata, a, b);
                    $display("immediate %d, mux_out %d",  immediate, mux_out);
                    $display("alu_out %d",  alu_out);
                    $display("readdata %d",  readdata);

                    #4
                    pc = i;
                    $display("---------------pc: %d", pc);

                end

            #340 $finish;
        end

endmodule

Khizar/verilog/single-cycle/vcd/combined_tb_clock.vcd
$date
	Fri Jul 21 02:44:26 2023
$end
$version
	Icarus Verilog
$end
$timescale
	1s
$end
$scope module combined_tb $end
$var wire 1 ! overflow $end
$var wire 1 " zero $end
$var wire 32 # writedata [31:0] $end
$var wire 1 $ regwrite $end
$var wire 32 % readdata [31:0] $end
$var wire 32 & mux_out [31:0] $end
$var wire 1 ' memwrite $end
$var wire 1 ( memtoreg $end
$var wire 1 ) memread $end
$var wire 32 * instruction [31:0] $end
$var wire 32 + immediate [31:0] $end
$var wire 1 , branch $end
$var wire 32 - b [31:0] $end
$var wire 1 . alusrc $end
$var wire 2 / aluop [1:0] $end
$var wire 4 0 aluctl [3:0] $end
$var wire 32 1 alu_out [31:0] $end
$var wire 32 2 a [31:0] $end
$var reg 1 3 clk $end
$var reg 10 4 pc [9:0] $end
$var integer 32 5 i [31:0] $end
$scope module uutA $end
$var wire 1 3 clk $end
$var wire 10 6 pc [9:0] $end
$var reg 32 7 instruction [31:0] $end
$upscope $end
$scope module uutB $end
$var wire 1 3 clk $end
$var wire 7 8 instruction [6:0] $end
$var reg 2 9 aluop [1:0] $end
$var reg 1 . alusrc $end
$var reg 1 , branch $end
$var reg 1 ) memread $end
$var reg 1 ( memtoreg $end
$var reg 1 ' memwrite $end
$var reg 1 $ regwrite $end
$upscope $end
$scope module uutC $end
$var wire 2 : aluop [1:0] $end
$var wire 3 ; func3 [2:0] $end
$var wire 7 < func7 [6:0] $end
$var reg 4 = aluctl [3:0] $end
$upscope $end
$scope module uutD $end
$var wire 32 > instruction [31:0] $end
$var reg 32 ? result [31:0] $end
$upscope $end
$scope module uutE $end
$var wire 32 @ in2 [31:0] $end
$var wire 1 . s $end
$var wire 32 A in1 [31:0] $end
$var reg 32 B out [31:0] $end
$upscope $end
$scope module uutF $end
$var wire 1 3 clk $end
$var wire 5 C rd [4:0] $end
$var wire 1 $ regwrite $end
$var wire 5 D rs1 [4:0] $end
$var wire 5 E rs2 [4:0] $end
$var wire 32 F writedata [31:0] $end
$var reg 32 G readdata1 [31:0] $end
$var reg 32 H readdata2 [31:0] $end
$upscope $end
$scope module uutG $end
$var wire 32 I a [31:0] $end
$var wire 4 J aluctl [3:0] $end
$var wire 32 K b [31:0] $end
$var wire 1 ! overflow $end
$var wire 1 " zero $end
$var reg 32 L out [31:0] $end
$upscope $end
$scope module uutH $end
$var wire 10 M address [9:0] $end
$var wire 1 3 clk $end
$var wire 1 ) memread $end
$var wire 1 ' memwrite $end
$var wire 32 N writedata [31:0] $end
$var reg 32 O readdata [31:0] $end
$upscope $end
$scope module uutI $end
$var wire 32 P in1 [31:0] $end
$var wire 32 Q in2 [31:0] $end
$var wire 1 ( s $end
$var reg 32 R out [31:0] $end
$upscope $end
$upscope $end
$enddefinitions $end
#0
$dumpvars
bx R
bx Q
bx P
bx O
bx N
bx M
bx L
bx K
bx J
bx I
bx H
bx G
bx F
bx E
bx D
bx C
bx B
bx A
bx @
bx ?
bx >
bx =
bx <
bx ;
bx :
bx 9
bx 8
bx 7
b0 6
b0 5
b0 4
03
bx 2
bx 1
bx 0
bx /
x.
bx -
x,
bx +
bx *
x)
x(
x'
bx &
bx %
x$
bx #
x"
z!
$end
#1
b1 +
b1 ?
b1 @
b10 0
b10 =
b10 J
b0 ;
b0 <
b1010 C
b1 E
b0 D
b10011 8
b100000000010100010011 *
b100000000010100010011 7
b100000000010100010011 >
b0 /
b0 9
b0 :
0,
0(
0'
0)
0$
0.
13
#2
03
#3
b1 #
b1 F
b1 R
b1 M
0"
b1 1
b1 L
b1 P
b1 &
b1 B
b1 K
b0 2
b0 G
b0 I
1$
1.
13
#4
03
#5
13
#6
03
#7
13
#8
03
#9
13
b1 5
#10
03
#11
13
#12
03
#13
13
#14
03
#15
13
#16
03
#17
13
#18
03
b10 5
b1 4
b1 6
#19
b1011 C
b1010 D
b101010000010110010011 *
b101010000010110010011 7
b101010000010110010011 >
13
#20
03
#21
b10 #
b10 F
b10 R
b10 M
b10 1
b10 L
b10 P
b1 2
b1 G
b1 I
13
#22
03
#23
13
#24
03
#25
13
#26
03
#27
b11 #
b11 F
b11 R
b11 M
b11 1
b11 L
b11 P
b10 &
b10 B
b10 K
b10 +
b10 ?
b10 @
b1100 C
b10 E
b1001010000011000010011 *
b1001010000011000010011 7
b1001010000011000010011 >
13
b11 5
b10 4
b10 6
#28
03
#29
13
#30
03
#31
13
#32
03
#33
13
#34
03
#35
13
#36
03
b100 5
b11 4
b11 6
#37
b1 #
b1 F
b1 R
b1 M
b1 1
b1 L
b1 P
b0 &
b0 B
b0 K
b0 +
b0 ?
b0 @
b0 C
b0 E
b0 D
b0 8
b0 *
b0 7
b0 >
13
#38
03
#39
b0 #
b0 F
b0 R
b0 M
1"
b0 1
b0 L
b0 P
b0 -
b0 A
b0 H
b0 N
b0 2
b0 G
b0 I
0$
0.
13
#40
03
#41
13
#42
03
#43
13
#44
03
#45
b1001 +
b1001 ?
b1001 @
b10 ;
b1001 C
b1010 E
b100011 8
b101000000010010010100011 *
b101000000010010010100011 7
b101000000010010010100011 >
13
b101 5
b100 4
b100 6
#46
03
#47
b1001 #
b1001 F
b1001 R
b1001 M
0"
b1001 1
b1001 L
b1001 P
b1001 &
b1001 B
b1001 K
b1 -
b1 A
b1 H
b1 N
1'
1.
13
#48
03
#49
13
#50
03
#51
13
#52
03
#53
13
#54
03
b110 5
b101 4
b101 6
#55
b0 #
b0 F
b0 R
b0 M
1"
b0 1
b0 L
b0 P
b0 &
b0 B
b0 K
b0 +
b0 ?
b0 @
b0 ;
b0 C
b0 E
b0 8
b0 *
b0 7
b0 >
13
#56
03
#57
0'
0.
b0 -
b0 A
b0 H
b0 N
13
#58
03
#59
13
#60
03
#61
13
#62
03
#63
b11 +
b11 ?
b11 @
b1101 C
b11 E
b1010 D
b10011 8
b1101010000011010010011 *
b1101010000011010010011 7
b1101010000011010010011 >
13
b111 5
b110 4
b110 6
#64
03
#65
b100 #
b100 F
b100 R
b100 M
b11 &
b11 B
b11 K
0"
b100 1
b100 L
b100 P
1$
1.
bx -
bx A
bx H
bx N
b1 2
b1 G
b1 I
13
#66
03
#67
13
#68
03
#69
13
#70
03
#71
13
#72
03
b1000 5
b111 4
b111 6
#73
b1 #
b1 F
b1 R
b1 M
b1 1
b1 L
b1 P
b0 &
b0 B
b0 K
b0 +
b0 ?
b0 @
b1110 C
b1011 E
b1101 D
b110011 8
b101101101000011100110011 *
b101101101000011100110011 7
b101101101000011100110011 >
13
#74
03
#75
b110 #
b110 F
b110 R
b110 M
b110 1
b110 L
b110 P
b10 &
b10 B
b10 K
b10 -
b10 A
b10 H
b10 N
b100 2
b100 G
b100 I
b10 /
b10 9
b10 :
0.
13
#76
03
#77
13
#78
03
#79
13
#80
03
#81
b1111 C
b0 E
b1110 D
b10011 8
b1110000011110010011 *
b1110000011110010011 7
b1110000011110010011 >
13
b1001 5
b1000 4
b1000 6
#82
03
#83
b110 #
b110 F
b110 R
b110 M
b110 1
b110 L
b110 P
b0 &
b0 B
b0 K
b0 -
b0 A
b0 H
b0 N
b110 2
b110 G
b110 I
b0 /
b0 9
b0 :
1.
13
#84
03
#85
13
#86
03
#87
13
#88
03
#89
13
#90
03
b1010 5
b1001 4
b1001 6
#91
b100000 <
b10000 C
b1011 E
b1111 D
b110011 8
b1000000101101111000100000110011 *
b1000000101101111000100000110011 7
b1000000101101111000100000110011 >
13
#92
03
#93
b100 #
b100 F
b100 R
b100 M
b100 1
b100 L
b100 P
b110 0
b110 =
b110 J
b10 &
b10 B
b10 K
b10 /
b10 9
b10 :
0.
b10 -
b10 A
b10 H
b10 N
13
#94
03
#95
13
#96
03
#97
13
#98
03
#99
b1000 #
b1000 F
b1000 R
b1000 M
b1000 1
b1000 L
b1000 P
b10 0
b10 =
b10 J
b0 <
b10001 C
b0 E
b10000 D
b10011 8
b10000000100010010011 *
b10000000100010010011 7
b10000000100010010011 >
13
b1011 5
b1010 4
b1010 6
#100
03
#101
b100 #
b100 F
b100 R
b100 M
b0 &
b0 B
b0 K
b100 1
b100 L
b100 P
b0 /
b0 9
b0 :
1.
b0 -
b0 A
b0 H
b0 N
b100 2
b100 G
b100 I
13
#102
03
#103
13
#104
03
#105
13
#106
03
#107
13
#108
03
b1100 5
b1011 4
b1011 6
#109
b1000 #
b1000 F
b1000 R
b1000 M
b1000 1
b1000 L
b1000 P
b100 &
b100 B
b100 K
b100 +
b100 ?
b100 @
b10 ;
b100 C
b1011 E
b0 D
b100011 8
b101100000010001000100011 *
b101100000010001000100011 7
b101100000010001000100011 >
13
#110
03
#111
b100 #
b100 F
b100 R
b100 M
b100 1
b100 L
b100 P
b10 -
b10 A
b10 H
b10 N
b0 2
b0 G
b0 I
1'
0$
13
#112
03
#113
13
#114
03
#115
13
#116
03
#117
b0 #
b0 F
b0 R
b0 M
1"
b0 1
b0 L
b0 P
b0 &
b0 B
b0 K
b0 +
b0 ?
b0 @
b0 ;
b0 C
b0 E
b0 8
b0 *
b0 7
b0 >
13
b1101 5
b1100 4
b1100 6
#118
03
#119
b0 -
b0 A
b0 H
b0 N
0'
0.
13
#120
03
#121
13
#122
03
#123
13
#124
03
#125
13
#126
03
b1110 5
b1101 4
b1101 6
#127
b101 +
b101 ?
b101 @
b10 ;
b101 C
b1100 E
b100011 8
b110000000010001010100011 *
b110000000010001010100011 7
b110000000010001010100011 >
13
#128
03
#129
b101 #
b101 F
b101 R
b101 M
0"
b101 1
b101 L
b101 P
b101 &
b101 B
b101 K
1'
1.
b11 -
b11 A
b11 H
b11 N
13
#130
03
#131
13
#132
03
#133
13
#134
03
#135
b0 #
b0 F
b0 R
b0 M
1"
b0 1
b0 L
b0 P
b0 &
b0 B
b0 K
b0 +
b0 ?
b0 @
b0 ;
b0 C
b0 E
b0 8
b0 *
b0 7
b0 >
13
b1111 5
b1110 4
b1110 6
#136
03
#137
0'
0.
b0 -
b0 A
b0 H
b0 N
13
#138
03
#139
13
#140
03
#141
13
#142
03
#143
13
#144
03
b10000 5
b1111 4
b1111 6
#145
b101 +
b101 ?
b101 @
b10 ;
b10010 C
b101 E
b11 8
b10100000010100100000011 *
b10100000010100100000011 7
b10100000010100100000011 >
13
#146
03
#147
b101 M
0"
b101 1
b101 L
b101 P
bx #
bx F
bx R
b101 &
b101 B
b101 K
bx -
bx A
bx H
bx N
1)
1$
1(
1.
13
#148
03
#149
b11 #
b11 F
b11 R
b11 %
b11 O
b11 Q
13
#150
03
#151
13
#152
03
#153
b0 M
1"
b0 1
b0 L
b0 P
b0 &
b0 B
b0 K
b0 +
b0 ?
b0 @
b0 ;
b0 C
b0 E
b0 8
b0 *
b0 7
b0 >
13
b10001 5
b10000 4
b10000 6
#154
03
#155
b0 #
b0 F
b0 R
b0 -
b0 A
b0 H
b0 N
0(
0)
0$
0.
13
#156
03
#157
13
#158
03
#159
13
#160
03
#161
13
#162
03
b10010 5
b10001 4
b10001 6
#163
b10011 C
b10010 D
b10011 8
b10010000100110010011 *
b10010000100110010011 7
b10010000100110010011 >
13
#164
03
#165
b11 #
b11 F
b11 R
b11 M
0"
b11 1
b11 L
b11 P
1$
1.
b11 2
b11 G
b11 I
13
#166
03
#167
13
#168
03
#169
13
#170
03
#171
b111 ;
b10100 C
b1010 E
b110011 8
b101010010111101000110011 *
b101010010111101000110011 7
b101010010111101000110011 >
13
b10011 5
b10010 4
b10010 6
#172
03
#173
b1 #
b1 F
b1 R
b1 M
b1 1
b1 L
b1 P
b0 0
b0 =
b0 J
b1 &
b1 B
b1 K
b10 /
b10 9
b10 :
0.
b1 -
b1 A
b1 H
b1 N
13
#174
03
#175
13
#176
03
#177
13
#178
03
#179
13
#180
03
b10100 5
b10011 4
b10011 6
#181
b100 #
b100 F
b100 R
b100 M
b100 1
b100 L
b100 P
b10 0
b10 =
b10 J
b0 ;
b10111 C
b0 E
b10100 D
b10011 8
b10100000101110010011 *
b10100000101110010011 7
b10100000101110010011 >
13
#182
03
#183
b1 #
b1 F
b1 R
b1 M
b1 1
b1 L
b1 P
b0 &
b0 B
b0 K
b0 -
b0 A
b0 H
b0 N
b1 2
b1 G
b1 I
b0 /
b0 9
b0 :
1.
13
#184
03
#185
13
#186
03
#187
13
#188
03
#189
b110 ;
b10101 C
b1011 E
b10000 D
b110011 8
b101110000110101010110011 *
b101110000110101010110011 7
b101110000110101010110011 >
13
b10101 5
b10100 4
b10100 6
#190
03
#191
b110 #
b110 F
b110 R
b110 M
b110 1
b110 L
b110 P
b1 0
b1 =
b1 J
b10 &
b10 B
b10 K
b10 -
b10 A
b10 H
b10 N
b100 2
b100 G
b100 I
b10 /
b10 9
b10 :
0.
13
#192
03
#193
13
#194
03
#195
13
#196
03
#197
13
#198
03
b10110 5
b10101 4
b10101 6
#199
b10 0
b10 =
b10 J
b0 ;
b11000 C
b0 E
b10101 D
b10011 8
b10101000110000010011 *
b10101000110000010011 7
b10101000110000010011 >
13
#200
03
#201
b110 #
b110 F
b110 R
b110 M
b0 &
b0 B
b0 K
b110 1
b110 L
b110 P
b0 /
b0 9
b0 :
1.
b0 -
b0 A
b0 H
b0 N
b110 2
b110 G
b110 I
13
#202
03
#203
13
#204
03
#205
13
#206
03
#207
b100 ;
b10110 C
b1110 E
b10001 D
b110011 8
b111010001100101100110011 *
b111010001100101100110011 7
b111010001100101100110011 >
13
b10111 5
b10110 4
b10110 6
#208
03
#209
b10 #
b10 F
b10 R
b10 M
b1100 0
b1100 =
b1100 J
b110 &
b110 B
b110 K
b10 1
b10 L
b10 P
b10 /
b10 9
b10 :
0.
b110 -
b110 A
b110 H
b110 N
b100 2
b100 G
b100 I
13
#210
03
#211
13
#212
03
#213
13
#214
03
#215
13
#216
03
b11000 5
b10111 4
b10111 6
#217
b1010 #
b1010 F
b1010 R
b1010 M
b1010 1
b1010 L
b1010 P
b10 0
b10 =
b10 J
b0 ;
b11001 C
b0 E
b10110 D
b10011 8
b10110000110010010011 *
b10110000110010010011 7
b10110000110010010011 >
13
#218
03
#219
b10 #
b10 F
b10 R
b10 M
b10 1
b10 L
b10 P
b0 &
b0 B
b0 K
b0 -
b0 A
b0 H
b0 N
b10 2
b10 G
b10 I
b0 /
b0 9
b0 :
1.
13
#220
03
#221
13
#222
03
#223
13
#224
03
#225
b0 C
b0 D
b0 8
b0 *
b0 7
b0 >
13
b11001 5
b11000 4
b11000 6
#226
03
#227
b0 #
b0 F
b0 R
b0 M
1"
b0 1
b0 L
b0 P
b0 2
b0 G
b0 I
0$
0.
13
#228
03
#229
13
#230
03
#231
13
#232
03
#233
13
#234
03
b11010 5
b11001 4
b11001 6
#235
b100 +
b100 ?
b100 @
b10 ;
b11010 C
b100 E
b11 8
b10000000010110100000011 *
b10000000010110100000011 7
b10000000010110100000011 >
13
#236
03
#237
b100 M
0"
b100 1
b100 L
b100 P
b11 #
b11 F
b11 R
b100 &
b100 B
b100 K
1)
1$
1(
1.
b1000 -
b1000 A
b1000 H
b1000 N
13
#238
03
#239
b10 #
b10 F
b10 R
b10 %
b10 O
b10 Q
13
#240
03
#241
13
#242
03
#243
b0 M
1"
b0 1
b0 L
b0 P
b0 &
b0 B
b0 K
b0 +
b0 ?
b0 @
b0 ;
b11011 C
b0 E
b11010 D
b10011 8
b11010000110110010011 *
b11010000110110010011 7
b11010000110110010011 >
13
b11011 5
b11010 4
b11010 6
#244
03
#245
b10 M
0"
b10 1
b10 L
b10 P
b10 #
b10 F
b10 R
0)
0(
b0 -
b0 A
b0 H
b0 N
b10 2
b10 G
b10 I
b11 %
b11 O
b11 Q
13
#246
03
#247
13
#248
03
#249
13
#250
03
#251
13
#252
03
b11100 5
b11011 4
b11011 6
#253
b0 C
b0 D
b0 8
b0 *
b0 7
b0 >
13
#254
03
#255
b0 #
b0 F
b0 R
b0 M
1"
b0 1
b0 L
b0 P
b0 2
b0 G
b0 I
0$
0.
13
#256
03
#257
13
#258
03
#259
13
#260
03
#261
b1001 +
b1001 ?
b1001 @
b10 ;
b11110 C
b1001 E
b11 8
b100100000010111100000011 *
b100100000010111100000011 7
b100100000010111100000011 >
13
b11101 5
b11100 4
b11100 6
#262
03
#263
b1001 M
0"
b1001 1
b1001 L
b1001 P
b11 #
b11 F
b11 R
b1001 &
b1001 B
b1001 K
bx -
bx A
bx H
bx N
1)
1$
1(
1.
13
#264
03
#265
b1 #
b1 F
b1 R
b1 %
b1 O
b1 Q
13
#266
03
#267
13
#268
03
#269
13
#270
03
b11110 5
b11101 4
b11101 6
#271
b0 M
1"
b0 1
b0 L
b0 P
b0 &
b0 B
b0 K
b0 +
b0 ?
b0 @
b0 ;
b0 C
b0 E
b0 8
b0 *
b0 7
b0 >
13
#272
03
#273
b0 #
b0 F
b0 R
0(
0)
0$
0.
b0 -
b0 A
b0 H
b0 N
b11 %
b11 O
b11 Q
13
#274
03
#275
13
#276
03
#277
13
#278
03
#279
b11111 C
b11110 D
b10011 8
b11110000111110010011 *
b11110000111110010011 7
b11110000111110010011 >
13
b11111 5
b11110 4
b11110 6
#280
03
#281
b1 #
b1 F
b1 R
b1 M
0"
b1 1
b1 L
b1 P
1$
1.
b1 2
b1 G
b1 I
13
#282
03
#283
13
#284
03
#285
13
#286
03
#287
13
#288
03
b100000 5
b11111 4
b11111 6
#289
bx ;
bx <
bx C
bx E
bx D
bx 8
bx *
bx 7
bx >
13
#290
03
#291
bx #
bx F
bx R
bx M
x"
bx 1
bx L
bx P
bx &
bx B
bx K
bx -
bx A
bx H
bx N
bx 2
bx G
bx I
0$
0.
13
