Khizar/verilog/single-cycle/onlyclock/mux2_1.v
module mux2_1(in1, in2, s, out);

    input [31:0] in1, in2;
    input s;

    output reg [31:0] out;

    always @ (in1, in2, s)
        begin
            if (s == 0)
                out <= in1;
            else
                out <= in2;
        end

endmodule

Khizar/verilog/single-cycle/onlyclock/datamemory.v
module datamemory(clk, address, writedata, memread, memwrite, readdata);

    input clk;
    input memread, memwrite;
    input [31:0] writedata;
    input [9:0] address; // change later
    
    output wire [31:0] readdata;

    reg [7:0] memfile [0:1023]; // increase memory size later

    assign readdata = (memread == 1) ? {memfile[address+3], memfile[address+2], memfile[address+1], memfile[address]} : 0;

    always @ (posedge clk)
        begin
            if (memwrite == 1)
                {memfile[address+3], memfile[address+2], memfile[address+1], memfile[address]} <= writedata;
        end

endmodule

Khizar/verilog/singleImplem/alu.v
module alu(aluctl, a, b, out, zero, overflow);

    input [3:0] aluctl; 

    input [31:0] a;
    input [31:0] b;

    output reg [31:0] out;
    output zero, overflow;

    assign zero = (out == 0);

    always @ (aluctl, a, b)
        begin
            case (aluctl)
                0: out <= a & b;
                1: out <= a | b;
                2: out <= a + b;
                6: out <= a - b;
                7: out <= (a < b ? 1: 0);
                12: out <= ~(a | b);
                default: out <= 0;
            endcase
        end

endmodule

Khizar/verilog/single-cycle/old/alucontrol.v
module alucontrol(aluop, func7, func3, aluctl);

    input [1:0] aluop;
    input [6:0] func7;
    input [2:0] func3;

    output reg [3:0] aluctl;

    always @ (aluop, func7, func3)
        begin
          if (aluop == 2'b00)
            aluctl <= 4'b0010;
          else if (aluop == 2'b01) 
            aluctl <= 4'b0110;
          else if (aluop == 2'b10)
            begin
              if (func7 == 7'b0000000)
                begin
                  if (func3 == 3'b000)
                    aluctl <= 4'b0010;
                  else if (func3 == 3'b111)
                    aluctl <= 4'b0000;
                  else if (func3 == 3'b100)
                    aluctl <= 4'b1100;
                  else if (func3 == 3'b110)
                    aluctl <= 4'b0001;
                end
              else if (func7 == 7'b0100000)
                begin
                  if (func3 == 3'b000)
                    aluctl <= 4'b0110;
                end
            end
        end

endmodule

Khizar/verilog/single-cycle/riscv-single-cycle/immediategen.v
module immediategen(instruction, result);

    //opcode types
    localparam I = 7'b0010011;
    localparam S = 7'b0100011;
    localparam SB = 7'b1100011;
    localparam I_LD = 7'b0000011;

    input [31:0] instruction;

    output reg [31:0] result;

    always @ (instruction)
        begin
            case (instruction[6:0])
                I_LD, I: 
                    result <= {{20{instruction[31]}}, instruction[31:20]};
                S: 
                    result <= {{19{instruction[31]}}, instruction[31:25], instruction[11:7]};
                SB: 
                    result <= {{18{instruction[31]}}, instruction[31], instruction[7], instruction[30:25], instruction[11:8], 1'b0};
                    
                default: result <= 0;
            endcase
        end

endmodule

Khizar/verilog/single-cycle/riscv-single-cycle/registerfile.v
module registerfile(clk, rs1, rs2, rd, writedata, regwrite, readdata1, readdata2);

    input clk;
    input [4:0] rs1, rs2, rd;
    input [31:0] writedata;
    input regwrite;

    output wire [31:0] readdata1, readdata2;

    reg [31:0] regfile [0:31];

    initial 
      begin
        regfile[0] <= 0;    
      end

    assign readdata1 = regfile[rs1];
    assign readdata2 = regfile[rs2];

    always @ (posedge clk)
        begin
          if (regwrite == 1 & rd != 0)
              regfile[rd] <= writedata;          
        end

endmodule

Khizar/verilog/single-cycle/riscv-single-cycle/maincontrol.v
module maincontrol(opcode, branch, memread, memtoreg, aluop, memwrite, alusrc, regwrite);

  //opcode types
  localparam I    = 7'b0010011;
  localparam S    = 7'b0100011;
  localparam SB   = 7'b1100011;
  localparam I_LD = 7'b0000011;
  localparam R    = 7'b0110011;

  input [6:0] opcode;

  output reg branch, memread, memtoreg, memwrite, alusrc, regwrite;
  output reg [1:0] aluop;

  always @ (opcode)
    begin
      case (opcode)
        R:
          {aluop, alusrc, memtoreg, regwrite, memread, memwrite, branch} <= 8'b10_0_0_1_0_0_0;
        I_LD:
          {aluop, alusrc, memtoreg, regwrite, memread, memwrite, branch} <= 8'b00_1_1_1_1_0_0;
        S:
          {aluop, alusrc, memtoreg, regwrite, memread, memwrite, branch} <= 8'b00_1_0_0_0_1_0;
        SB:
          {aluop, alusrc, memtoreg, regwrite, memread, memwrite, branch} <= 8'b01_0_0_0_0_0_1;
        I: // for addi (i-type)
          {aluop, alusrc, memtoreg, regwrite, memread, memwrite, branch} <= 8'b00_1_0_1_0_0_0;
        default:
          {aluop, alusrc, memtoreg, regwrite, memread, memwrite, branch} <= 8'b00_0_0_0_0_0_0;
      endcase
    end

endmodule

Khizar/verilog/single-cycle/riscv-single-cycle/instructionmemory.v
module instructionmemory(pc, instruction);

    input [9:0] pc; // change later
    
    output wire [31:0] instruction;

    reg [7:0] memfile [0:1023]; // increase memory size later

    assign instruction = {memfile[pc+3], memfile[pc+2], memfile[pc+1], memfile[pc]};

    initial
        begin // write instructions here
            //  addi x10, x0,  1
            {memfile[3], memfile[2], memfile[1], memfile[0]} <= 32'b0000_0000_0000___00000___000___00000___001_0011;          //  x10     =   1

            //  addi x11, x10, 1
            {memfile[7], memfile[6], memfile[5], memfile[4]} <= 32'b0000_0000_0001___01010___000___00000___001_0011;          //  x11     =   2

            //  addi x12, x10, 2
            {memfile[11], memfile[10], memfile[9], memfile[8]} <= 32'b0000_0000_0010___01010___000___00000___001_0011;         //  x12     =   3

            //  nop
            {memfile[15], memfile[14], memfile[13], memfile[12]} <= 32'b0000_0000_0000___00000___000___00000___000_0000;        //  nop

            //  sw   x10, 9(x0)
            {memfile[19], memfile[18], memfile[17], memfile[16]}  <= 32'b0000000___01010___00000___010___01001___010_0011;       //  mem[9]  =   1

            //  nop
            {memfile[23], memfile[22], memfile[21], memfile[20]} <= 32'b0000_0000_0000___00000___000___00000___000_0000;        //  nop

            //  addi x13, x10, 3
            {memfile[27], memfile[26], memfile[25], memfile[24]} <= 32'b0000_0000_0011___01010___000___00000___001_0011;         //  x13     =   4

            //  add  x14, x13, x11 (rd, rs1, rs2)
            {memfile[31], memfile[30], memfile[29], memfile[28]} <= 32'b0000000___01011___01101___000___00000___011_0011;        //  x14     =   6   (x14 = x11 + x13)

            //  addi x15, x14, 0
            {memfile[35], memfile[34], memfile[33], memfile[32]} <= 32'b0000_0000_0000___01110___000___00000___001_0011;        //  x15     =   6   (x15 = x14 + 0)

            //  sub x16, x15, x11
            {memfile[39], memfile[38], memfile[37], memfile[36]} <= 32'b0100000___01011___01111___000___00000___011_0011;        // x16     =   4   (x16 = x15 - x11)

            //  addi x17, x16, 0
            {memfile[43], memfile[42], memfile[41], memfile[40]} <= 32'b0000_0000_0000___10000___000___00000___001_0011;        //  x17     =   4   (x17 = x16 + 0)

            //  sw   x11, 4(x0)
            {memfile[47], memfile[46], memfile[45], memfile[44]} <= 32'b0000000___01011___00000___010___00100___010_0011;       //  mem[4]  =   2

            //  nop
            {memfile[51], memfile[50], memfile[49], memfile[48]} <= 32'b0000_0000_0000___00000___000___00000___000_0000;       //  nop

            //  sw   x12, 5(x0)
            {memfile[55], memfile[54], memfile[53], memfile[52]} <= 32'b0000000___01100___00000___010___00101___010_0011;       // mem[5]  =   3

            //  nop
            {memfile[59], memfile[58], memfile[57], memfile[56]} <= 32'b0000_0000_0000___00000___000___00000___000_0000;       //  nop

            //  lw   x18, 5(x0)
            {memfile[63], memfile[62], memfile[61], memfile[60]} <= 32'b0000_0000_0101___00000___010___00000___000_0011;       //  x18     =   mem[5]  =   3

            //  nop
            {memfile[67], memfile[66], memfile[65], memfile[64]} <= 32'b0000_0000_0000___00000___000___00000___000_0000;       //  nop

            //  addi x19, x18, 0
            {memfile[71], memfile[70], memfile[69], memfile[68]} <= 32'b0000_0000_0000___10010___000___00000___001_0011;       //  x19     =   3   (x19 = x18 + 0)

            //  and  x20, x10, x18
            {memfile[75], memfile[74], memfile[73], memfile[72]} <= 32'b0000000___01010___10010___111___00000___011_0011;      //  x20     =   1   (x20 = x10 & x18)
            //  x10 = 0000_0000_0000_0000_0000_0000_0000_0001
            //  x18 = 0000_0000_0000_0000_0000_0000_0000_0011
            //  x20 = 0000_0000_0000_0000_0000_0000_0000_0001

            //  addi x23, x20, 0
            {memfile[79], memfile[78], memfile[77], memfile[76]} <= 32'b0000_0000_0000___10100___000___10111___001_0011;          //  x23     =   1   (x23 = x20 + 0)

            ///////////////////////
            //  or  x21, x11, x16
            {memfile[83], memfile[82], memfile[81], memfile[80]} <= 32'b0000000___01011___01111___000___00000___011_0011;       //  x21     =   6   (x21 = x11 | x16)
            //  x11 = 0000_0000_0000_0000_0000_0000_0000_0010
            //  x16 = 0000_0000_0000_0000_0000_0000_0000_0100
            //  x21 = 0000_0000_0000_0000_0000_0000_0000_0110

            //  addi x24, x21, 0
            {memfile[87], memfile[86], memfile[85], memfile[84]} <= 32'b0000_0000_0000___10101___000___00000___001_0011;       //  x24     =   6   (x24 = x21 + 0)

            //  xor  x22, x14, x17
            {memfile[91], memfile[90], memfile[89], memfile[88]} <= 32'b0000000___01110___10001___100___00000___011_0011;      //  x22     =   2   (x22 = x14 xor x17)
            //  x14 = 0000_0000_0000_0000_0000_0000_0000_0110
            //  x17 = 0000_0000_0000_0000_0000_0000_0000_0100
            //  x22 = 0000_0000_0000_0000_0000_0000_0000_0010

            //  addi x25, x22, 0
            {memfile[95], memfile[94], memfile[93], memfile[92]} <= 32'b0000_0000_0000___10110___000___00000___001_0011;      //  x25     =   2   (x25 = x22 + 0)

            //  nop
            {memfile[99], memfile[98], memfile[97], memfile[96]} <= 32'b0000_0000_0000___00000___000___00000___000_0000;      //  nop

            //  lw   x26, 4(x0)
            {memfile[103], memfile[102], memfile[101], memfile[100]} <= 32'b0000_0000_0100___00000___010___00000___000_0011;     //  x26     =   mem[4]  = 2

            //  addi x27, x26, 0
            {memfile[107], memfile[106], memfile[105], memfile[104]} <= 32'b0000_0000_0000___11010___000___00000___001_0011;      //  x27     =   2   (x27 = x26 + 0)

            //  nop
            {memfile[111], memfile[110], memfile[109], memfile[108]} <= 32'b0000_0000_0000___00000___000___00000___000_0000;      //  nop

            //  lw   x30, 9(x0)
            {memfile[115], memfile[114], memfile[113], memfile[112]} <= 32'b0000_0000_1001___00000___010___00000___000_0011;     //  x30     =   mem[9]  =   1

            //  nop
            {memfile[119], memfile[118], memfile[117], memfile[116]} <= 32'b0000_0000_0000___00000___000___00000___000_0000;     //  nop

            //  addi x31, x30, 0
            {memfile[123], memfile[122], memfile[121], memfile[120]} <= 32'b0000_0000_0000___11110___000___00000___001_0011;     //  x31     =   1

            //  sw   x24, 8(x16)
            {memfile[127], memfile[126], memfile[125], memfile[124]} <= 32'b0000000___11000___10000___010___00000___010_0011;   // mem[12]  =   6

            //  sw   x25, 9(x17)
            {memfile[131], memfile[130], memfile[129], memfile[128]} <= 32'b0000000___11001___10001___010___00000___010_0011;   // mem[13]  =   2

            //  sw   x19, 13(x10)
            {memfile[135], memfile[134], memfile[133], memfile[132]} <= 32'b0000000___10011___01010___010___00000___010_0011;   // mem[14]  =   3

            //  sw   x30, 12(x18)
            {memfile[139], memfile[138], memfile[137], memfile[136]} <= 32'b0000000___11110___10010___010___00000___010_0011;   // mem[15]  =   1

            //  lw   x5, 10(x11)
            {memfile[143], memfile[142], memfile[141], memfile[140]} <= 32'b0000000___01010___01011___010___00000___000_0011;   // x5   =   mem[12]  =   6

            //  lw   x6, 10(x12)
            {memfile[147], memfile[146], memfile[145], memfile[144]} <= 32'b0000000___01010___01100___010___00000___000_0011;   // x6   =   mem[13]  =   2

            //  lw   x7, 8(x15)
            {memfile[151], memfile[150], memfile[149], memfile[148]} <= 32'b0000000___01000___01111___010___00000___000_0011;   // x7   =   mem[14]  =   3

            //  lw   x8, 13(x25)
            {memfile[155], memfile[154], memfile[153], memfile[152]} <= 32'b0000000___01101___11001___010___01000___000_0011;        // x8   =   mem[15]  =   1

            //  addi x4, x5, 0
            {memfile[159], memfile[158], memfile[157], memfile[156]} <= 32'b0000_0000_0000___00101___000___00100___001_0011;         //  x5     =   6
            
            //  addi x4, x6, 0
            {memfile[163], memfile[162], memfile[161], memfile[160]} <= 32'b0000_0000_0000___00110___000___00100___001_0011;         //  x6     =   2

            //  addi x4, x7, 0
            {memfile[167], memfile[166], memfile[165], memfile[164]} <= 32'b0000_0000_0000___00111___000___00100___001_0011;         //  x7     =   3

            //  addi x4, x8, 0
            {memfile[171], memfile[170], memfile[169], memfile[168]} <= 32'b0000_0000_0000___01000___000___00100___001_0011;         //  x8     =   1
        end

endmodule

Khizar/verilog/single-cycle/riscv-single-cycle/combined_tb.v
`include "maincontrol.v"
`include "alucontrol.v"
`include "alu.v"
`include "registerfile.v"
`include "instructionmemory.v"
`include "adder.v"
`include "datamemory.v"
`include "immediategen.v"
`include "mux2_1.v"

module combined_tb;

    reg [9:0] pc;
    reg clk;
    
    wire branch, memread, memtoreg, memwrite, alusrc, regwrite, zero;
    wire [1:0] aluop;
    wire [3:0] aluctl;
    wire [31:0] instruction, a, b, immediate, mux_out, alu_out, writedata, readdata, sumA, sumB;

    instructionmemory   uutA(pc, instruction);
    maincontrol         uutB(instruction[6:0], branch, memread, memtoreg, aluop, memwrite, alusrc, regwrite);
    registerfile        uutF(clk, instruction[19:15], instruction[24:20], instruction[11:7], writedata, regwrite, a, b);
    immediategen        uutD(instruction, immediate);
    alucontrol          uutC(aluop, instruction[31:25], instruction[14:12], aluctl);                   
    mux2_1              uutE(b, immediate, alusrc, mux_out);
    alu                 uutG(aluctl, a, mux_out, alu_out, zero, overflow);
    datamemory          uutH(clk, alu_out[9:0], b, memread, memwrite, readdata); // decreased address to 10 bits, change later
    mux2_1              uutI(alu_out, readdata, memtoreg, writedata);

    //adder               uutJ(pc, 4, pc);
    // adder               uutK(immediate, pc, sumB);
    // mux2_1              uutL(sumA, sumB, select, pc);

    integer i;

    always #1 clk = ~clk;

    initial
        begin
            $dumpfile("../vcd/combined_tb_b.vcd");
            $dumpvars(2, combined_tb);

            $readmemh("ins", uutA.memfile);
            pc = -1;
            clk = 0;

            #2
            for(i = 0; i < 200; i = i + 4)
                begin
                    #6
                    pc = i;
                    $display("te pc: %d", pc);
                end

            #340 $finish;
        end

endmodule

Khizar/verilog/single-cycle/vcd/combined_tb_b.vcd
$date
	Wed Jul 26 16:44:18 2023
$end
$version
	Icarus Verilog
$end
$timescale
	1s
$end
$scope module combined_tb $end
$var wire 1 ! overflow $end
$var wire 1 " zero $end
$var wire 32 # writedata [31:0] $end
$var wire 1 $ regwrite $end
$var wire 32 % readdata [31:0] $end
$var wire 32 & mux_out [31:0] $end
$var wire 1 ' memwrite $end
$var wire 1 ( memtoreg $end
$var wire 1 ) memread $end
$var wire 32 * instruction [31:0] $end
$var wire 32 + immediate [31:0] $end
$var wire 1 , branch $end
$var wire 32 - b [31:0] $end
$var wire 1 . alusrc $end
$var wire 2 / aluop [1:0] $end
$var wire 4 0 aluctl [3:0] $end
$var wire 32 1 alu_out [31:0] $end
$var wire 32 2 a [31:0] $end
$var reg 1 3 clk $end
$var reg 10 4 pc [9:0] $end
$var integer 32 5 i [31:0] $end
$scope module uutA $end
$var wire 10 6 pc [9:0] $end
$var wire 32 7 instruction [31:0] $end
$upscope $end
$scope module uutB $end
$var wire 7 8 opcode [6:0] $end
$var reg 2 9 aluop [1:0] $end
$var reg 1 . alusrc $end
$var reg 1 , branch $end
$var reg 1 ) memread $end
$var reg 1 ( memtoreg $end
$var reg 1 ' memwrite $end
$var reg 1 $ regwrite $end
$upscope $end
$scope module uutC $end
$var wire 2 : aluop [1:0] $end
$var wire 3 ; func3 [2:0] $end
$var wire 7 < func7 [6:0] $end
$var reg 4 = aluctl [3:0] $end
$upscope $end
$scope module uutD $end
$var wire 32 > instruction [31:0] $end
$var reg 32 ? result [31:0] $end
$upscope $end
$scope module uutE $end
$var wire 32 @ in2 [31:0] $end
$var wire 1 . s $end
$var wire 32 A out [31:0] $end
$var wire 32 B in1 [31:0] $end
$upscope $end
$scope module uutF $end
$var wire 1 3 clk $end
$var wire 5 C rd [4:0] $end
$var wire 32 D readdata1 [31:0] $end
$var wire 32 E readdata2 [31:0] $end
$var wire 1 $ regwrite $end
$var wire 5 F rs1 [4:0] $end
$var wire 5 G rs2 [4:0] $end
$var wire 32 H writedata [31:0] $end
$upscope $end
$scope module uutG $end
$var wire 32 I a [31:0] $end
$var wire 4 J aluctl [3:0] $end
$var wire 32 K b [31:0] $end
$var wire 1 ! overflow $end
$var wire 1 " zero $end
$var reg 32 L out [31:0] $end
$upscope $end
$scope module uutH $end
$var wire 10 M address [9:0] $end
$var wire 1 3 clk $end
$var wire 1 ) memread $end
$var wire 1 ' memwrite $end
$var wire 32 N writedata [31:0] $end
$var wire 32 O readdata [31:0] $end
$upscope $end
$scope module uutI $end
$var wire 32 P in1 [31:0] $end
$var wire 32 Q in2 [31:0] $end
$var wire 1 ( s $end
$var wire 32 R out [31:0] $end
$upscope $end
$upscope $end
$enddefinitions $end
#0
$dumpvars
bx R
bx Q
bx P
bx O
bx N
bx M
bx L
bx K
bx J
bx I
bx H
bx G
bx F
bx E
bx D
bx C
bx B
bx A
bx @
bx ?
bx >
bx =
bx <
bx ;
bx :
bx 9
bx 8
bx 7
b1111111111 6
bx 5
b1111111111 4
03
bx 2
bx 1
bx 0
bx /
x.
bx -
x,
bx +
bx *
x)
x(
x'
bx &
bx %
x$
bx #
x"
z!
$end
#1
13
#2
03
b0 5
#3
13
#4
03
#5
13
#6
03
#7
13
#8
b1 M
b1 #
b1 H
b1 R
b0 %
b0 O
b0 Q
b1 &
b1 A
b1 K
b10 0
b10 =
b10 J
0"
b1 1
b1 L
b1 P
b0 /
b0 9
b0 :
1.
0(
1$
0)
0'
0,
b1 +
b1 ?
b1 @
b0 <
b1 G
b0 ;
b0 2
b0 D
b0 I
b0 F
b1010 C
b10011 8
03
b100 5
b100000000010100010011 *
b100000000010100010011 7
b100000000010100010011 >
b0 4
b0 6
#9
13
#10
03
#11
13
#12
03
#13
13
#14
b10 #
b10 H
b10 R
b10 M
b10 1
b10 L
b10 P
b1 2
b1 D
b1 I
b1010 F
b1011 C
03
b1000 5
b101010000010110010011 *
b101010000010110010011 7
b101010000010110010011 >
b100 4
b100 6
#15
13
#16
03
#17
13
#18
03
#19
13
#20
b11 #
b11 H
b11 R
b11 M
b11 1
b11 L
b11 P
b10 &
b10 A
b10 K
b10 +
b10 ?
b10 @
b10 G
b1100 C
03
b1100 5
b1001010000011000010011 *
b1001010000011000010011 7
b1001010000011000010011 >
b1000 4
b1000 6
#21
13
#22
03
#23
13
#24
03
#25
13
#26
1"
b0 #
b0 H
b0 R
b0 M
b0 &
b0 A
b0 K
b0 1
b0 L
b0 P
b0 +
b0 ?
b0 @
b0 -
b0 B
b0 E
b0 N
b0 G
b0 2
b0 D
b0 I
b0 F
b0 C
03
b10000 5
b10011 *
b10011 7
b10011 >
b1100 4
b1100 6
#27
13
#28
03
#29
13
#30
03
#31
13
#32
0$
1'
b1 -
b1 B
b1 E
b1 N
b1010 G
b10 ;
b100011 8
03
b10100 5
b101000000010000000100011 *
b101000000010000000100011 7
b101000000010000000100011 >
b10000 4
b10000 6
#33
13
#34
03
#35
13
#36
03
#37
13
#38
1$
0'
b0 -
b0 B
b0 E
b0 N
b0 G
b0 ;
b10011 8
03
b11000 5
b10011 *
b10011 7
b10011 >
b10100 4
b10100 6
#39
13
#40
03
#41
13
#42
03
#43
13
#44
b100 #
b100 H
b100 R
b100 M
b11 &
b11 A
b11 K
0"
b100 1
b100 L
b100 P
b11 +
b11 ?
b11 @
bx -
bx B
bx E
bx N
b11 G
b1 2
b1 D
b1 I
b1010 F
b1101 C
03
b11100 5
b1101010000011010010011 *
b1101010000011010010011 7
b1101010000011010010011 >
b11000 4
b11000 6
#45
13
#46
03
#47
13
#48
03
#49
13
#50
b110 #
b110 H
b110 R
b110 M
b10 &
b10 A
b10 K
b110 1
b110 L
b110 P
b10 /
b10 9
b10 :
0.
b0 +
b0 ?
b0 @
b10 -
b10 B
b10 E
b10 N
b1011 G
b100 2
b100 D
b100 I
b1101 F
b1110 C
b110011 8
03
b100000 5
b101101101000011100110011 *
b101101101000011100110011 7
b101101101000011100110011 >
b11100 4
b11100 6
#51
13
#52
03
#53
13
#54
03
#55
13
#56
b110 1
b110 L
b110 P
b0 /
b0 9
b0 :
1.
b0 &
b0 A
b0 K
b0 -
b0 B
b0 E
b0 N
b0 G
b110 2
b110 D
b110 I
b1110 F
b1111 C
b10011 8
03
b100100 5
b1110000011110010011 *
b1110000011110010011 7
b1110000011110010011 >
b100000 4
b100000 6
#57
13
#58
03
#59
13
#60
03
#61
13
#62
b100 #
b100 H
b100 R
b100 M
b100 1
b100 L
b100 P
b110 0
b110 =
b110 J
b10 &
b10 A
b10 K
b10 /
b10 9
b10 :
0.
b100000 <
b10 -
b10 B
b10 E
b10 N
b1011 G
b1111 F
b10000 C
b110011 8
03
b101000 5
b1000000101101111000100000110011 *
b1000000101101111000100000110011 7
b1000000101101111000100000110011 >
b100100 4
b100100 6
#63
13
#64
03
#65
13
#66
03
#67
13
#68
b10 0
b10 =
b10 J
b100 1
b100 L
b100 P
b0 /
b0 9
b0 :
1.
b0 &
b0 A
b0 K
b0 <
b0 -
b0 B
b0 E
b0 N
b0 G
b100 2
b100 D
b100 I
b10000 F
b10001 C
b10011 8
03
b101100 5
b10000000100010010011 *
b10000000100010010011 7
b10000000100010010011 >
b101000 4
b101000 6
#69
13
#70
03
#71
13
#72
03
#73
13
#74
b0 #
b0 H
b0 R
b0 M
1"
b0 1
b0 L
b0 P
0$
1'
b10 -
b10 B
b10 E
b10 N
b1011 G
b0 2
b0 D
b0 I
b0 F
b10 ;
b0 C
b100011 8
03
b110000 5
b101100000010000000100011 *
b101100000010000000100011 7
b101100000010000000100011 >
b101100 4
b101100 6
#75
13
#76
03
#77
13
#78
03
#79
13
#80
1$
0'
b0 -
b0 B
b0 E
b0 N
b0 G
b0 ;
b10011 8
03
b110100 5
b10011 *
b10011 7
b10011 >
b110000 4
b110000 6
#81
13
#82
03
#83
13
#84
03
#85
13
#86
b100 #
b100 H
b100 R
b100 M
0"
b100 1
b100 L
b100 P
b100 &
b100 A
b100 K
0$
1'
b100 +
b100 ?
b100 @
b11 -
b11 B
b11 E
b11 N
b1100 G
b10 ;
b100 C
b100011 8
03
b111000 5
b110000000010001000100011 *
b110000000010001000100011 7
b110000000010001000100011 >
b110100 4
b110100 6
#87
13
#88
03
#89
13
#90
03
#91
13
#92
b0 #
b0 H
b0 R
b0 M
1"
b0 1
b0 L
b0 P
b0 &
b0 A
b0 K
1$
0'
b0 +
b0 ?
b0 @
b0 -
b0 B
b0 E
b0 N
b0 G
b0 ;
b0 C
b10011 8
03
b111100 5
b10011 *
b10011 7
b10011 >
b111000 4
b111000 6
#93
13
#94
03
#95
13
#96
03
#97
13
#98
b100 M
0"
b100 1
b100 L
b100 P
b11 #
b11 H
b11 R
b11 %
b11 O
b11 Q
b100 &
b100 A
b100 K
1(
1)
b100 +
b100 ?
b100 @
bx -
bx B
bx E
bx N
b100 G
b10 ;
b10010 C
b11 8
03
b1000000 5
b10000000010100100000011 *
b10000000010100100000011 7
b10000000010100100000011 >
b111100 4
b111100 6
#99
13
#100
03
#101
13
#102
03
#103
13
#104
b0 M
1"
b0 1
b0 L
b0 P
b0 #
b0 H
b0 R
b0 %
b0 O
b0 Q
b0 &
b0 A
b0 K
0(
0)
b0 +
b0 ?
b0 @
b0 -
b0 B
b0 E
b0 N
b0 G
b0 ;
b0 C
b10011 8
03
b1000100 5
b10011 *
b10011 7
b10011 >
b1000000 4
b1000000 6
#105
13
#106
03
#107
13
#108
03
#109
13
#110
b11 #
b11 H
b11 R
b11 M
0"
b11 1
b11 L
b11 P
b11 2
b11 D
b11 I
b10010 F
b10011 C
03
b1001000 5
b10010000100110010011 *
b10010000100110010011 7
b10010000100110010011 >
b1000100 4
b1000100 6
#111
13
#112
03
#113
13
#114
03
#115
13
#116
b0 0
b0 =
b0 J
b1 #
b1 H
b1 R
b1 M
b11 &
b11 A
b11 K
b1 1
b1 L
b1 P
b10 /
b10 9
b10 :
0.
b11 -
b11 B
b11 E
b11 N
b10010 G
b1 2
b1 D
b1 I
b1010 F
b111 ;
b10100 C
b110011 8
03
b1001100 5
b1001001010111101000110011 *
b1001001010111101000110011 7
b1001001010111101000110011 >
b1001000 4
b1001000 6
#117
13
#118
03
#119
13
#120
03
#121
13
#122
b1 #
b1 H
b1 R
b1 M
0"
b1 1
b1 L
b1 P
b10 0
b10 =
b10 J
b0 /
b0 9
b0 :
1.
b0 &
b0 A
b0 K
b0 -
b0 B
b0 E
b0 N
b0 G
b10100 F
b0 ;
b10111 C
b10011 8
03
b1010000 5
b10100000101110010011 *
b10100000101110010011 7
b10100000101110010011 >
b1001100 4
b1001100 6
#123
13
#124
03
#125
13
#126
03
#127
13
#128
b1 0
b1 =
b1 J
b110 #
b110 H
b110 R
b110 M
b100 &
b100 A
b100 K
b110 1
b110 L
b110 P
b10 /
b10 9
b10 :
0.
b100 -
b100 B
b100 E
b100 N
b10000 G
b110 ;
b10101 C
b10 2
b10 D
b10 I
b1011 F
b110011 8
03
b1010100 5
b1000001011110101010110011 *
b1000001011110101010110011 7
b1000001011110101010110011 >
b1010000 4
b1010000 6
#129
13
#130
03
#131
13
#132
03
#133
13
#134
b10 0
b10 =
b10 J
b0 /
b0 9
b0 :
1.
b0 &
b0 A
b0 K
b0 -
b0 B
b0 E
b0 N
b0 G
b110 2
b110 D
b110 I
b10101 F
b0 ;
b11000 C
b10011 8
03
b1011000 5
b10101000110000010011 *
b10101000110000010011 7
b10101000110000010011 >
b1010100 4
b1010100 6
#135
13
#136
03
#137
13
#138
03
#139
13
#140
b10 #
b10 H
b10 R
b10 M
b10 1
b10 L
b10 P
b1100 0
b1100 =
b1100 J
b100 &
b100 A
b100 K
b10 /
b10 9
b10 :
0.
b100 -
b100 B
b100 E
b100 N
b10001 G
b100 ;
b10110 C
b1110 F
b110011 8
03
b1011100 5
b1000101110100101100110011 *
b1000101110100101100110011 7
b1000101110100101100110011 >
b1011000 4
b1011000 6
#141
13
#142
03
#143
13
#144
03
#145
13
#146
b10 1
b10 L
b10 P
b10 0
b10 =
b10 J
b0 /
b0 9
b0 :
1.
b0 &
b0 A
b0 K
b0 -
b0 B
b0 E
b0 N
b0 G
b10 2
b10 D
b10 I
b10110 F
b0 ;
b11001 C
b10011 8
03
b1100000 5
b10110000110010010011 *
b10110000110010010011 7
b10110000110010010011 >
b1011100 4
b1011100 6
#147
13
#148
03
#149
13
#150
03
#151
13
#152
b0 #
b0 H
b0 R
b0 M
1"
b0 1
b0 L
b0 P
b0 2
b0 D
b0 I
b0 F
b0 C
03
b1100100 5
b10011 *
b10011 7
b10011 >
b1100000 4
b1100000 6
#153
13
#154
03
#155
13
#156
03
#157
13
#158
b100 M
0"
b100 1
b100 L
b100 P
b11 #
b11 H
b11 R
b11 %
b11 O
b11 Q
b100 &
b100 A
b100 K
1(
1)
b100 +
b100 ?
b100 @
bx -
bx B
bx E
bx N
b100 G
b10 ;
b11010 C
b11 8
03
b1101000 5
b10000000010110100000011 *
b10000000010110100000011 7
b10000000010110100000011 >
b1100100 4
b1100100 6
#159
13
#160
03
#161
13
#162
03
#163
13
#164
b11 M
b11 #
b11 H
b11 R
b0 %
b0 O
b0 Q
b0 &
b0 A
b0 K
b11 1
b11 L
b11 P
0(
0)
b0 +
b0 ?
b0 @
b0 -
b0 B
b0 E
b0 N
b0 G
b11 2
b11 D
b11 I
b11010 F
b0 ;
b11011 C
b10011 8
03
b1101100 5
b11010000110110010011 *
b11010000110110010011 7
b11010000110110010011 >
b1101000 4
b1101000 6
#165
13
#166
03
#167
13
#168
03
#169
13
#170
b0 #
b0 H
b0 R
b0 M
1"
b0 1
b0 L
b0 P
b0 2
b0 D
b0 I
b0 F
b0 C
03
b1110000 5
b10011 *
b10011 7
b10011 >
b1101100 4
b1101100 6
#171
13
#172
03
#173
13
#174
03
#175
13
#176
b10 #
b10 H
b10 R
b10 %
b10 O
b10 Q
1(
1)
b10 ;
b11110 C
b11 8
03
b1110100 5
b10111100000011 *
b10111100000011 7
b10111100000011 >
b1110000 4
b1110000 6
#177
13
#178
03
#179
13
#180
03
#181
13
#182
b0 #
b0 H
b0 R
b0 %
b0 O
b0 Q
0(
0)
b0 ;
b0 C
b10011 8
03
b1111000 5
b10011 *
b10011 7
b10011 >
b1110100 4
b1110100 6
#183
13
#184
03
#185
13
#186
03
#187
13
#188
b10 #
b10 H
b10 R
b10 M
0"
b10 1
b10 L
b10 P
b10 2
b10 D
b10 I
b11110 F
b11111 C
03
b1111100 5
b11110000111110010011 *
b11110000111110010011 7
b11110000111110010011 >
b1111000 4
b1111000 6
#189
13
#190
03
#191
13
#192
03
#193
13
#194
b1100 #
b1100 H
b1100 R
b1100 M
b1000 &
b1000 A
b1000 K
b1100 1
b1100 L
b1100 P
0$
1'
b1000 +
b1000 ?
b1000 @
b110 -
b110 B
b110 E
b110 N
b11000 G
b100 2
b100 D
b100 I
b10000 F
b10 ;
b1000 C
b100011 8
03
b10000000 5
b1100010000010010000100011 *
b1100010000010010000100011 7
b1100010000010010000100011 >
b1111100 4
b1111100 6
#195
13
#196
03
#197
13
#198
03
#199
13
#200
b10000 #
b10000 H
b10000 R
b10000 M
b10000 1
b10000 L
b10000 P
b1100 &
b1100 A
b1100 K
b1100 +
b1100 ?
b1100 @
b10 -
b10 B
b10 E
b10 N
b11001 G
b1100 C
b10001 F
03
b10000100 5
b1100110001010011000100011 *
b1100110001010011000100011 7
b1100110001010011000100011 >
b10000000 4
b10000000 6
#201
13
#202
03
#203
13
#204
03
#205
13
