Khizar/verilog/single-cycle/onlyclock/mux2_1.v
module mux2_1(in1, in2, s, out);

    input [31:0] in1, in2;
    input s;

    output reg [31:0] out;

    always @ (in1, in2, s)
        begin
            if (s == 0)
                out <= in1;
            else
                out <= in2;
        end

endmodule

Khizar/verilog/single-cycle/onlyclock/datamemory.v
module datamemory(clk, address, writedata, memread, memwrite, readdata);

    input clk;
    input memread, memwrite;
    input [31:0] writedata;
    input [9:0] address; // change later
    
    output wire [31:0] readdata;

    reg [7:0] memfile [0:1023]; // increase memory size later

    assign readdata = (memread == 1) ? {memfile[address+3], memfile[address+2], memfile[address+1], memfile[address]} : 0;

    always @ (posedge clk)
        begin
            if (memwrite == 1)
                {memfile[address+3], memfile[address+2], memfile[address+1], memfile[address]} <= writedata;
        end

endmodule

Khizar/verilog/singleImplem/alu.v
module alu(aluctl, a, b, out, zero, overflow);

    input [3:0] aluctl; 

    input [31:0] a;
    input [31:0] b;

    output reg [31:0] out;
    output zero, overflow;

    assign zero = (out == 0);

    always @ (aluctl, a, b)
        begin
            case (aluctl)
                0: out <= a & b;
                1: out <= a | b;
                2: out <= a + b;
                6: out <= a - b;
                7: out <= (a < b ? 1: 0);
                12: out <= ~(a | b);
                default: out <= 0;
            endcase
        end

endmodule

Khizar/verilog/single-cycle/old/alucontrol.v
module alucontrol(aluop, func7, func3, aluctl);

    input [1:0] aluop;
    input [6:0] func7;
    input [2:0] func3;

    output reg [3:0] aluctl;

    always @ (aluop, func7, func3)
        begin
          if (aluop == 2'b00)
            aluctl <= 4'b0010;
          else if (aluop == 2'b01) 
            aluctl <= 4'b0110;
          else if (aluop == 2'b10)
            begin
              if (func7 == 7'b0000000)
                begin
                  if (func3 == 3'b000)
                    aluctl <= 4'b0010;
                  else if (func3 == 3'b111)
                    aluctl <= 4'b0000;
                  else if (func3 == 3'b100)
                    aluctl <= 4'b1100;
                  else if (func3 == 3'b110)
                    aluctl <= 4'b0001;
                end
              else if (func7 == 7'b0100000)
                begin
                  if (func3 == 3'b000)
                    aluctl <= 4'b0110;
                end
            end
        end

endmodule

Khizar/verilog/single-cycle/onlyclock/immediategen.v
module immediategen(instruction, result);

    input [31:0] instruction;

    output reg [31:0] result;

    always @ (instruction)
        begin
            case (instruction[6:0])
                7'b0000011, 7'b0010011: result <= {{20{instruction[31]}}, instruction[31:20]};
                7'b0100011: result <= {{19{instruction[31]}}, instruction[31:25], instruction[11:7]};
                7'b1100011: result <= {{18{instruction[31]}}, instruction[31], instruction[7], instruction[30:25], instruction[11:8], 1'b0};
                    
                default: result <= 5;
            endcase
        end

endmodule

Khizar/verilog/single-cycle/riscv-single-cycle/registerfile.v
module registerfile(clk, rs1, rs2, rd, writedata, regwrite, readdata1, readdata2);

    input clk;
    input [4:0] rs1, rs2, rd;
    input [31:0] writedata;
    input regwrite;

    output wire [31:0] readdata1, readdata2;

    reg [31:0] regfile [0:31];

    initial 
      begin
        regfile[0] <= 0;    
      end

    assign readdata1 = regfile[rs1];
    assign readdata2 = regfile[rs2];

    always @ (posedge clk)
        begin
          if (regwrite == 1 & rd != 0)
              regfile[rd] <= writedata;          
        end

endmodule

Khizar/verilog/single-cycle/onlyclock/maincontrol.v
module maincontrol(clk, instruction, branch, memread, memtoreg, aluop, memwrite, alusrc, regwrite);

    input clk;
    input [6:0] instruction;

    output reg branch, memread, memtoreg, memwrite, alusrc, regwrite;
    output reg [1:0] aluop;

    always @ (instruction)
        begin
          case (instruction)
            7'b0110011: 
              begin
                alusrc <= 0;
                memtoreg <= 0;
                regwrite <= 1;
                memread <= 0;
                memwrite <= 0;
                branch <= 0;
                aluop <= 2'b10;
              end
            7'b0000011: 
              begin
                alusrc <= 1;
                memtoreg <= 1;
                regwrite <= 1;
                memread <= 1;
                memwrite <= 0;
                branch <= 0;
                aluop <= 2'b00;
              end
            7'b0100011:
              begin
                alusrc <= 1;
                regwrite <= 0;
                memread <= 0;
                memwrite <= 1;
                branch <= 0;
                aluop <= 2'b00;
              end
            7'b1100011: 
              begin
                alusrc <= 0;
                regwrite <= 0;
                memread <= 0;
                memwrite <= 0;
                branch <= 1;
                aluop <= 2'b01;
              end
            7'b0010011: // for addi (i-type)
              begin
                alusrc <= 1;
                regwrite <= 1;
                memtoreg <= 0;
                memread <= 0;
                memwrite <= 0;
                branch <= 0;
                aluop <= 2'b00;
              end

            default: 
              begin
                alusrc <= 0;
                regwrite <= 0;
                memread <= 0;
                memwrite <= 0;
                memtoreg <= 0;
                branch <= 0;
                aluop <= 2'b00;
              end
          endcase
        end

endmodule

Khizar/verilog/single-cycle/onlyclock/instructionmemory.v
module instructionmemory(clk, pc, instruction);

    input clk;
    input [9:0] pc; // change later
    
    output wire [31:0] instruction;

    reg [7:0] memfile [0:1023]; // increase memory size later

    initial
        begin // write instructions here
            // x0 = 0 already done

            //  addi x10, x0,  1     
            {memfile[3], memfile[2], memfile[1], memfile[0]} <= 32'b0000_0000_0001___00000___000___0101______0___001_0011;          //  x10     =   1

            //  addi x11, x10, 1
            memfile[1] <= 32'b0000_0000_0001___01010___000___01011___001_0011;          //  x11     =   2

            //  addi x12, x10, 2
            memfile[2] <= 32'b0000_0000_0010___01010___000___01100___001_0011;          //  x12     =   3
            
            //  nop
            memfile[3] <= 32'b0000_0000_0000___00000___000___00000___000_0000;          //  nop
            
            //  sw   x10, 9(x0)
            memfile[4]  <= 32'b0000000___01010___00000___010___01001___010_0011;        //  mem[9]  =   1

            //  nop
            memfile[5] <= 32'b0000_0000_0000___00000___000___00000___000_0000;          //  nop
            
            //  addi x13, x10, 3 
            memfile[6] <= 32'b0000_0000_0011___01010___000___01101___001_0011;          //  x13     =   4

            //  add  x14, x13, x11 (rd, rs1, rs2)                                                                                               
            memfile[7] <= 32'b0000000___01011___01101___000___01110___011_0011;         //  x14     =   6   (x14 = x11 + x13)

            //  addi x15, x14, 0
            memfile[8] <= 32'b0000_0000_0000___01110___000___01111___001_0011;          //  x15     =   6   (x15 = x14 + 0)

            //  sub x16, x15, x11
            memfile[9] <= 32'b0100000___01011___01111___000___10000___011_0011;          // x16     =   4   (x16 = x15 - x11)
                
            //  addi x17, x16, 0
            memfile[10] <= 32'b0000_0000_0000___10000___000___10001___001_0011;          //  x17     =   4   (x17 = x16 + 0)

            //  sw   x11, 4(x0)         
            memfile[11]  <= 32'b0000000___01011___00000___010___00100___010_0011;         //  mem[4]  =   2

            //  nop
            memfile[12] <= 32'b0000_0000_0000___00000___000___00000___000_0000;         //  nop

            //  sw   x12, 5(x0)         
            memfile[13] <= 32'b0000000___01100___00000___010___00101___010_0011;         // mem[5]  =   3

            //  nop
            memfile[14] <= 32'b0000_0000_0000___00000___000___00000___000_0000;         //  nop

            //  lw   x18, 5(x0)         
            memfile[15] <= 32'b0000_0000_0101___00000___010___10010___000_0011;         //  x18     =   mem[5]  =   3
            
            //  nop
            memfile[16] <= 32'b0000_0000_0000___00000___000___00000___000_0000;         //  nop

            //  addi x19, x18, 0
            memfile[17] <= 32'b0000_0000_0000___10010___000___10011___001_0011;          //  x19     =   3   (x19 = x18 + 0)

            //  and  x20, x10, x18                                                                                               
            memfile[18] <= 32'b0000000___01010___10010___111___10100___011_0011;         //  x20     =   1   (x20 = x10 & x18)
            //  x10 = 0000_0000_0000_0000_0000_0000_0000_0001
            //  x18 = 0000_0000_0000_0000_0000_0000_0000_0011
            //  x20 = 0000_0000_0000_0000_0000_0000_0000_0001

            //  addi x23, x20, 0
            memfile[19] <= 32'b0000_0000_0000___10100___000___10111___001_0011;          //  x23     =   1   (x23 = x20 + 0)

            //  or  x21, x11, x16                                                                                               
            memfile[20] <= 32'b0000000___01011___10000___110___10101___011_0011;         //  x21     =   6   (x21 = x11 | x16)
            //  x11 = 0000_0000_0000_0000_0000_0000_0000_0010
            //  x16 = 0000_0000_0000_0000_0000_0000_0000_0100
            //  x21 = 0000_0000_0000_0000_0000_0000_0000_0110

            //  addi x24, x21, 0
            memfile[21] <= 32'b0000_0000_0000___10101___000___11000___001_0011;          //  x24     =   6   (x24 = x21 + 0)

            // xor  x22, x14, x17                                                                                               
            memfile[22] <= 32'b0000000___01110___10001___100___10110___011_0011;         //  x22     =   2   (x22 = x14 xor x17)
            //  x14 = 0000_0000_0000_0000_0000_0000_0000_0110
            //  x17 = 0000_0000_0000_0000_0000_0000_0000_0100
            //  x22 = 0000_0000_0000_0000_0000_0000_0000_0010

            //  addi x25, x22, 0
            memfile[23] <= 32'b0000_0000_0000___10110___000___11001___001_0011;          //  x25     =   2   (x25 = x22 + 0)

            //  nop
            memfile[24] <= 32'b0000_0000_0000___00000___000___00000___000_0000;         //  nop
            
            //  lw   x26, 4(x0)         
            memfile[25] <= 32'b0000_0000_0100___00000___010___11010___000_0011;         //  x26     =   mem[4]  = 2
                
            //  addi x27, x26, 0
            memfile[26] <= 32'b0000_0000_0000___11010___000___11011___001_0011;          //  x27     =   2   (x27 = x26 + 0)

            //  nop
            memfile[27] <= 32'b0000_0000_0000___00000___000___00000___000_0000;         //  nop

            //  lw   x30, 9(x0)         
            memfile[28] <= 32'b0000_0000_1001___00000___010___11110___000_0011;         //  x30     =   mem[9]  =   1
            //  nop
            memfile[29] <= 32'b0000_0000_0000___00000___000___00000___000_0000;         //  nop

            //  addi x31, x30, 0
            memfile[30] <= 32'b0000_0000_0000___11110___000___11111___001_0011;         //  x31     =   1

            //new test
            //  sw   x24, 8(x16)         
            memfile[31] <= 32'b0000000___11000___10000___010___01000___010_0011;        // mem[12]  =   6

            //  sw   x25, 9(x17)         
            memfile[32] <= 32'b0000000___11001___10001___010___01001___010_0011;        // mem[13]  =   2

            //  sw   x19, 13(x10)         
            memfile[33] <= 32'b0000000___10011___01010___010___01101___010_0011;        // mem[14]  =   3

            //  sw   x30, 12(x18)         
            memfile[34] <= 32'b0000000___11110___10010___010___01100___010_0011;        // mem[15]  =   1

            //  lw   x5, 10(x11)         
            memfile[35] <= 32'b0000000___01010___01011___010___00101___000_0011;        // x5   =   mem[12]  =   6

            //  lw   x6, 10(x12)         
            memfile[36] <= 32'b0000000___01010___01100___010___00110___000_0011;        // x6   =   mem[13]  =   2

            //  lw   x7, 8(x15)         
            memfile[37] <= 32'b0000000___01000___01111___010___00111___000_0011;        // x7   =   mem[14]  =   3

            //  lw   x8, 13(x25)         
            memfile[38] <= 32'b0000000___01101___11001___010___01000___000_0011;        // x8   =   mem[15]  =   1

            //  addi x4, x5, 0
            memfile[39] <= 32'b0000_0000_0000___00101___000___00100___001_0011;         //  x5     =   6
            
            //  addi x4, x6, 0
            memfile[40] <= 32'b0000_0000_0000___00110___000___00100___001_0011;         //  x6     =   2

            //  addi x4, x7, 0
            memfile[41] <= 32'b0000_0000_0000___00111___000___00100___001_0011;         //  x7     =   3

            //  addi x4, x8, 0
            memfile[42] <= 32'b0000_0000_0000___01000___000___00100___001_0011;         //  x8     =   1

        end

    
    assign instruction = {memfile[pc+3], memfile[pc+2], memfile[pc+1], memfile[pc]};


    //        ins[7:0]
    //        ins[15:0]
    //        .....
    //        ....

endmodule

Khizar/verilog/single-cycle/onlyclock/combined_tb.v
`include "maincontrol.v"
`include "alucontrol.v"
`include "alu.v"
`include "registerfile.v"
`include "instructionmemory.v"
`include "adder.v"
`include "datamemory.v"
`include "immediategen.v"
`include "mux2_1.v"

module combined_tb;

    reg [9:0] pc;
    reg clk;
    
    wire branch, memread, memtoreg, memwrite, alusrc, regwrite, zero;
    wire [1:0] aluop;
    wire [3:0] aluctl;
    wire [31:0] instruction, a, b, immediate, mux_out, alu_out, writedata, readdata, sumA, sumB;

    instructionmemory   uutA(clk, pc, instruction);
    maincontrol         uutB(clk, instruction[6:0], branch, memread, memtoreg, aluop, memwrite, alusrc, regwrite);
    registerfile        uutF(clk, instruction[19:15], instruction[24:20], instruction[11:7], writedata, regwrite, a, b);
    immediategen        uutD(instruction, immediate);
    alucontrol          uutC(aluop, instruction[31:25], instruction[14:12], aluctl);                   
    mux2_1              uutE(b, immediate, alusrc, mux_out);
    alu                 uutG(aluctl, a, mux_out, alu_out, zero, overflow);
    datamemory          uutH(clk, alu_out[9:0], b, memread, memwrite, readdata); // decreased address to 10 bits, change later
    mux2_1              uutI(alu_out, readdata, memtoreg, writedata);

    //adder               uutJ(pc, 4, pc);
    // adder               uutK(immediate, pc, sumB);
    // mux2_1              uutL(sumA, sumB, select, pc);

    integer i;

    always #1 clk = ~clk;

    initial
        begin
            $dumpfile("../vcd/combined_tb_clock.vcd");
            $dumpvars(2, combined_tb);

            pc = 0;
            clk = 0;

            for(i = 0; i < 44; i = i + 1)
                begin
                    #5
                    $display("ins: %d", instruction);
                    $display("branch %d, memread %d, memtoreg %d, aluop %d, memwrite %d, alusrc %d, regwrite %d", branch, memread, memtoreg, aluop, memwrite, alusrc, regwrite);
                    $display("alu_ctl %d, writedata %d, a %d, b %",  aluctl, writedata, a, b);
                    $display("immediate %d, mux_out %d",  immediate, mux_out);
                    $display("alu_out %d",  alu_out);
                    $display("readdata %d",  readdata);

                    #4
                    pc = i;
                    $display("---------------pc: %d", pc);

                end

            #340 $finish;
        end

endmodule

Khizar/verilog/single-cycle/vcd/combined_tb_clock.vcd
$date
	Mon Jul 24 21:37:56 2023
$end
$version
	Icarus Verilog
$end
$timescale
	1s
$end
$scope module combined_tb $end
$var wire 1 ! overflow $end
$var wire 1 " zero $end
$var wire 32 # writedata [31:0] $end
$var wire 1 $ regwrite $end
$var wire 32 % readdata [31:0] $end
$var wire 32 & mux_out [31:0] $end
$var wire 1 ' memwrite $end
$var wire 1 ( memtoreg $end
$var wire 1 ) memread $end
$var wire 32 * instruction [31:0] $end
$var wire 32 + immediate [31:0] $end
$var wire 1 , branch $end
$var wire 32 - b [31:0] $end
$var wire 1 . alusrc $end
$var wire 2 / aluop [1:0] $end
$var wire 4 0 aluctl [3:0] $end
$var wire 32 1 alu_out [31:0] $end
$var wire 32 2 a [31:0] $end
$var reg 1 3 clk $end
$var reg 10 4 pc [9:0] $end
$var integer 32 5 i [31:0] $end
$scope module uutA $end
$var wire 1 3 clk $end
$var wire 32 6 instruction [31:0] $end
$var wire 10 7 pc [9:0] $end
$upscope $end
$scope module uutB $end
$var wire 1 3 clk $end
$var wire 7 8 instruction [6:0] $end
$var reg 2 9 aluop [1:0] $end
$var reg 1 . alusrc $end
$var reg 1 , branch $end
$var reg 1 ) memread $end
$var reg 1 ( memtoreg $end
$var reg 1 ' memwrite $end
$var reg 1 $ regwrite $end
$upscope $end
$scope module uutC $end
$var wire 2 : aluop [1:0] $end
$var wire 3 ; func3 [2:0] $end
$var wire 7 < func7 [6:0] $end
$var reg 4 = aluctl [3:0] $end
$upscope $end
$scope module uutD $end
$var wire 32 > instruction [31:0] $end
$var reg 32 ? result [31:0] $end
$upscope $end
$scope module uutE $end
$var wire 32 @ in2 [31:0] $end
$var wire 1 . s $end
$var wire 32 A in1 [31:0] $end
$var reg 32 B out [31:0] $end
$upscope $end
$scope module uutF $end
$var wire 1 3 clk $end
$var wire 5 C rd [4:0] $end
$var wire 32 D readdata1 [31:0] $end
$var wire 32 E readdata2 [31:0] $end
$var wire 1 $ regwrite $end
$var wire 5 F rs1 [4:0] $end
$var wire 5 G rs2 [4:0] $end
$var wire 32 H writedata [31:0] $end
$upscope $end
$scope module uutG $end
$var wire 32 I a [31:0] $end
$var wire 4 J aluctl [3:0] $end
$var wire 32 K b [31:0] $end
$var wire 1 ! overflow $end
$var wire 1 " zero $end
$var reg 32 L out [31:0] $end
$upscope $end
$scope module uutH $end
$var wire 10 M address [9:0] $end
$var wire 1 3 clk $end
$var wire 1 ) memread $end
$var wire 1 ' memwrite $end
$var wire 32 N writedata [31:0] $end
$var wire 32 O readdata [31:0] $end
$upscope $end
$scope module uutI $end
$var wire 32 P in1 [31:0] $end
$var wire 32 Q in2 [31:0] $end
$var wire 1 ( s $end
$var reg 32 R out [31:0] $end
$upscope $end
$upscope $end
$enddefinitions $end
#0
$dumpvars
b1 R
b0 Q
b1 P
b0 O
bx N
b1 M
b1 L
b1 K
b10 J
b0 I
b1 H
b1 G
b0 F
bx E
b0 D
b1010 C
b1 B
bx A
b1 @
b1 ?
b100000000010100010011 >
b10 =
b0 <
b0 ;
b0 :
b0 9
b10011 8
b0 7
b100000000010100010011 6
b0 5
b0 4
03
b0 2
b1 1
b10 0
b0 /
1.
bx -
0,
b1 +
b100000000010100010011 *
0)
0(
0'
b1 &
b0 %
1$
b1 #
0"
z!
$end
#1
13
#2
03
b1 5
#3
13
#4
b10 #
b10 H
b10 R
b10 M
b10 1
b10 L
b10 P
b1011 C
b1 2
b1 D
b1 I
b1010 F
03
b10 5
b101010000010110010011 *
b101010000010110010011 6
b101010000010110010011 >
b1 4
b1 7
#5
13
#6
b11 #
b11 H
b11 R
b11 M
b11 1
b11 L
b11 P
b10 &
b10 B
b10 K
b10 +
b10 ?
b10 @
b1100 C
b10 G
03
b11 5
b1001010000011000010011 *
b1001010000011000010011 6
b1001010000011000010011 >
b10 4
b10 7
#7
13
#8
1"
b0 #
b0 H
b0 R
b0 &
b0 B
b0 K
b0 M
b0 1
b0 L
b0 P
0$
0.
b101 +
b101 ?
b101 @
b0 C
b0 -
b0 A
b0 E
b0 N
b0 G
b0 2
b0 D
b0 I
b0 F
b0 8
03
b100 5
b0 *
b0 6
b0 >
b11 4
b11 7
#9
13
#10
b1001 #
b1001 H
b1001 R
b1001 M
0"
b1001 1
b1001 L
b1001 P
b1001 &
b1001 B
b1001 K
1'
1.
b1001 +
b1001 ?
b1001 @
b10 ;
b1001 C
b1 -
b1 A
b1 E
b1 N
b1010 G
b100011 8
03
b101 5
b101000000010010010100011 *
b101000000010010010100011 6
b101000000010010010100011 >
b100 4
b100 7
#11
13
#12
b0 #
b0 H
b0 R
b0 M
1"
b0 1
b0 L
b0 P
b0 &
b0 B
b0 K
0'
0.
b101 +
b101 ?
b101 @
b0 ;
b0 C
b0 -
b0 A
b0 E
b0 N
b0 G
b0 8
03
b110 5
b0 *
b0 6
b0 >
b101 4
b101 7
#13
13
#14
b100 #
b100 H
b100 R
b100 M
b11 &
b11 B
b11 K
0"
b100 1
b100 L
b100 P
1$
1.
b11 +
b11 ?
b11 @
b1101 C
bx -
bx A
bx E
bx N
b11 G
b1 2
b1 D
b1 I
b1010 F
b10011 8
03
b111 5
b1101010000011010010011 *
b1101010000011010010011 6
b1101010000011010010011 >
b110 4
b110 7
#15
13
#16
b110 #
b110 H
b110 R
b10 &
b10 B
b10 K
b110 M
b110 1
b110 L
b110 P
b10 /
b10 9
b10 :
0.
b101 +
b101 ?
b101 @
b1110 C
b10 -
b10 A
b10 E
b10 N
b1011 G
b100 2
b100 D
b100 I
b1101 F
b110011 8
03
b1000 5
b101101101000011100110011 *
b101101101000011100110011 6
b101101101000011100110011 >
b111 4
b111 7
#17
13
#18
b110 #
b110 H
b110 R
b110 M
b0 &
b0 B
b0 K
b110 1
b110 L
b110 P
b0 /
b0 9
b0 :
1.
b0 +
b0 ?
b0 @
b1111 C
b0 -
b0 A
b0 E
b0 N
b0 G
b110 2
b110 D
b110 I
b1110 F
b10011 8
03
b1001 5
b1110000011110010011 *
b1110000011110010011 6
b1110000011110010011 >
b1000 4
b1000 7
#19
13
#20
b100 #
b100 H
b100 R
b100 M
b100 1
b100 L
b100 P
b110 0
b110 =
b110 J
b10 &
b10 B
b10 K
b10 /
b10 9
b10 :
0.
b101 +
b101 ?
b101 @
b100000 <
b10000 C
b10 -
b10 A
b10 E
b10 N
b1011 G
b1111 F
b110011 8
03
b1010 5
b1000000101101111000100000110011 *
b1000000101101111000100000110011 6
b1000000101101111000100000110011 >
b1001 4
b1001 7
#21
13
#22
b100 #
b100 H
b100 R
b100 M
b10 0
b10 =
b10 J
b0 &
b0 B
b0 K
b100 1
b100 L
b100 P
b0 /
b0 9
b0 :
1.
b0 +
b0 ?
b0 @
b0 <
b10001 C
b0 -
b0 A
b0 E
b0 N
b0 G
b100 2
b100 D
b100 I
b10000 F
b10011 8
03
b1011 5
b10000000100010010011 *
b10000000100010010011 6
b10000000100010010011 >
b1010 4
b1010 7
#23
13
#24
b100 #
b100 H
b100 R
b100 &
b100 B
b100 K
b100 M
0"
b100 1
b100 L
b100 P
1'
0$
b100 +
b100 ?
b100 @
b10 ;
b100 C
b10 -
b10 A
b10 E
b10 N
b1011 G
b0 2
b0 D
b0 I
b0 F
b100011 8
03
b1100 5
b101100000010001000100011 *
b101100000010001000100011 6
b101100000010001000100011 >
b1011 4
b1011 7
#25
13
#26
b0 #
b0 H
b0 R
b0 M
1"
b0 1
b0 L
b0 P
b0 &
b0 B
b0 K
0'
0.
b101 +
b101 ?
b101 @
b0 ;
b0 C
b0 -
b0 A
b0 E
b0 N
b0 G
b0 8
03
b1101 5
b0 *
b0 6
b0 >
b1100 4
b1100 7
#27
13
#28
b101 #
b101 H
b101 R
b101 M
0"
b101 1
b101 L
b101 P
b101 &
b101 B
b101 K
1'
1.
b10 ;
b101 C
b11 -
b11 A
b11 E
b11 N
b1100 G
b100011 8
03
b1110 5
b110000000010001010100011 *
b110000000010001010100011 6
b110000000010001010100011 >
b1101 4
b1101 7
#29
13
#30
b0 #
b0 H
b0 R
b0 M
1"
b0 1
b0 L
b0 P
b0 &
b0 B
b0 K
0'
0.
b0 ;
b0 C
b0 -
b0 A
b0 E
b0 N
b0 G
b0 8
03
b1111 5
b0 *
b0 6
b0 >
b1110 4
b1110 7
#31
13
#32
b101 M
b11 #
b11 H
b11 R
0"
b101 1
b101 L
b101 P
b11 %
b11 O
b11 Q
b101 &
b101 B
b101 K
1)
1$
1(
1.
b10 ;
b10010 C
bx -
bx A
bx E
bx N
b101 G
b11 8
03
b10000 5
b10100000010100100000011 *
b10100000010100100000011 6
b10100000010100100000011 >
b1111 4
b1111 7
#33
13
#34
b0 M
1"
b0 1
b0 L
b0 P
b0 #
b0 H
b0 R
b0 &
b0 B
b0 K
b0 %
b0 O
b0 Q
0(
0)
0$
0.
b0 ;
b0 C
b0 -
b0 A
b0 E
b0 N
b0 G
b0 8
03
b10001 5
b0 *
b0 6
b0 >
b10000 4
b10000 7
#35
13
#36
b11 #
b11 H
b11 R
b11 M
0"
b11 1
b11 L
b11 P
1$
1.
b0 +
b0 ?
b0 @
b10011 C
b11 2
b11 D
b11 I
b10010 F
b10011 8
03
b10010 5
b10010000100110010011 *
b10010000100110010011 6
b10010000100110010011 >
b10001 4
b10001 7
#37
13
#38
b1 #
b1 H
b1 R
b1 M
b1 1
b1 L
b1 P
b0 0
b0 =
b0 J
b1 &
b1 B
b1 K
b10 /
b10 9
b10 :
0.
b101 +
b101 ?
b101 @
b111 ;
b10100 C
b1 -
b1 A
b1 E
b1 N
b1010 G
b110011 8
03
b10011 5
b101010010111101000110011 *
b101010010111101000110011 6
b101010010111101000110011 >
b10010 4
b10010 7
#39
13
#40
b10 0
b10 =
b10 J
b0 &
b0 B
b0 K
b0 /
b0 9
b0 :
1.
b0 +
b0 ?
b0 @
b0 ;
b10111 C
b0 -
b0 A
b0 E
b0 N
b0 G
b1 2
b1 D
b1 I
b10100 F
b10011 8
03
b10100 5
b10100000101110010011 *
b10100000101110010011 6
b10100000101110010011 >
b10011 4
b10011 7
#41
13
#42
b110 #
b110 H
b110 R
b1 0
b1 =
b1 J
b10 &
b10 B
b10 K
b110 M
b110 1
b110 L
b110 P
b10 /
b10 9
b10 :
0.
b101 +
b101 ?
b101 @
b110 ;
b10101 C
b10 -
b10 A
b10 E
b10 N
b1011 G
b100 2
b100 D
b100 I
b10000 F
b110011 8
03
b10101 5
b101110000110101010110011 *
b101110000110101010110011 6
b101110000110101010110011 >
b10100 4
b10100 7
#43
13
#44
b10 0
b10 =
b10 J
b0 &
b0 B
b0 K
b0 /
b0 9
b0 :
1.
b0 +
b0 ?
b0 @
b0 ;
b11000 C
b0 -
b0 A
b0 E
b0 N
b0 G
b110 2
b110 D
b110 I
b10101 F
b10011 8
03
b10110 5
b10101000110000010011 *
b10101000110000010011 6
b10101000110000010011 >
b10101 4
b10101 7
#45
13
#46
b10 #
b10 H
b10 R
b1100 0
b1100 =
b1100 J
b110 &
b110 B
b110 K
b10 M
b10 1
b10 L
b10 P
b10 /
b10 9
b10 :
0.
b101 +
b101 ?
b101 @
b100 ;
b10110 C
b110 -
b110 A
b110 E
b110 N
b1110 G
b100 2
b100 D
b100 I
b10001 F
b110011 8
03
b10111 5
b111010001100101100110011 *
b111010001100101100110011 6
b111010001100101100110011 >
b10110 4
b10110 7
#47
13
#48
b10 #
b10 H
b10 R
b10 M
b10 0
b10 =
b10 J
b0 &
b0 B
b0 K
b10 1
b10 L
b10 P
b0 /
b0 9
b0 :
1.
b0 +
b0 ?
b0 @
b0 ;
b11001 C
b0 -
b0 A
b0 E
b0 N
b0 G
b10 2
b10 D
b10 I
b10110 F
b10011 8
03
b11000 5
b10110000110010010011 *
b10110000110010010011 6
b10110000110010010011 >
b10111 4
b10111 7
#49
13
#50
b0 #
b0 H
b0 R
b0 M
1"
b0 1
b0 L
b0 P
0$
0.
b101 +
b101 ?
b101 @
b0 C
b0 2
b0 D
b0 I
b0 F
b0 8
03
b11001 5
b0 *
b0 6
b0 >
b11000 4
b11000 7
#51
13
#52
b100 M
b10 #
b10 H
b10 R
0"
b100 1
b100 L
b100 P
b10 %
b10 O
b10 Q
b100 &
b100 B
b100 K
1)
1$
1(
1.
b100 +
b100 ?
b100 @
b10 ;
b11010 C
bx -
bx A
bx E
bx N
b100 G
b11 8
03
b11010 5
b10000000010110100000011 *
b10000000010110100000011 6
b10000000010110100000011 >
b11001 4
b11001 7
#53
13
#54
b10 #
b10 H
b10 R
b0 &
b0 B
b0 K
b10 M
b0 %
b0 O
b0 Q
b10 1
b10 L
b10 P
0)
0(
b0 +
b0 ?
b0 @
b0 ;
b11011 C
b0 -
b0 A
b0 E
b0 N
b0 G
b10 2
b10 D
b10 I
b11010 F
b10011 8
03
b11011 5
b11010000110110010011 *
b11010000110110010011 6
b11010000110110010011 >
b11010 4
b11010 7
#55
13
#56
b0 #
b0 H
b0 R
b0 M
1"
b0 1
b0 L
b0 P
0$
0.
b101 +
b101 ?
b101 @
b0 C
b0 2
b0 D
b0 I
b0 F
b0 8
03
b11100 5
b0 *
b0 6
b0 >
b11011 4
b11011 7
#57
13
#58
b1001 M
b1 #
b1 H
b1 R
0"
b1001 1
b1001 L
b1001 P
b1 %
b1 O
b1 Q
b1001 &
b1001 B
b1001 K
1)
1$
1(
1.
b1001 +
b1001 ?
b1001 @
b10 ;
b11110 C
bx -
bx A
bx E
bx N
b1001 G
b11 8
03
b11101 5
b100100000010111100000011 *
b100100000010111100000011 6
b100100000010111100000011 >
b11100 4
b11100 7
#59
13
#60
b0 M
1"
b0 1
b0 L
b0 P
b0 #
b0 H
b0 R
b0 &
b0 B
b0 K
b0 %
b0 O
b0 Q
0(
0)
0$
0.
b101 +
b101 ?
b101 @
b0 ;
b0 C
b0 -
b0 A
b0 E
b0 N
b0 G
b0 8
03
b11110 5
b0 *
b0 6
b0 >
b11101 4
b11101 7
#61
13
#62
b1 #
b1 H
b1 R
b1 M
0"
b1 1
b1 L
b1 P
1$
1.
b0 +
b0 ?
b0 @
b11111 C
b1 2
b1 D
b1 I
b11110 F
b10011 8
03
b11111 5
b11110000111110010011 *
b11110000111110010011 6
b11110000111110010011 >
b11110 4
b11110 7
#63
13
#64
b1100 #
b1100 H
b1100 R
b1000 &
b1000 B
b1000 K
b1100 M
b1100 1
b1100 L
b1100 P
1'
0$
b1000 +
b1000 ?
b1000 @
b10 ;
b1000 C
b110 -
b110 A
b110 E
b110 N
b11000 G
b100 2
b100 D
b100 I
b10000 F
b100011 8
03
b100000 5
b1100010000010010000100011 *
b1100010000010010000100011 6
b1100010000010010000100011 >
b11111 4
b11111 7
#65
13
#66
b1101 #
b1101 H
b1101 R
b1101 M
b1101 1
b1101 L
b1101 P
b1001 &
b1001 B
b1001 K
b1001 +
b1001 ?
b1001 @
b1001 C
b10 -
b10 A
b10 E
b10 N
b11001 G
b10001 F
03
b100001 5
b1100110001010010010100011 *
b1100110001010010010100011 6
b1100110001010010010100011 >
b100000 4
b100000 7
#67
13
#68
b1110 #
b1110 H
b1110 R
b1101 &
b1101 B
b1101 K
b1110 M
b1110 1
b1110 L
b1110 P
b1101 +
b1101 ?
b1101 @
b1101 C
b11 -
b11 A
b11 E
b11 N
b10011 G
b1 2
b1 D
b1 I
b1010 F
03
b100010 5
b1001101010010011010100011 *
b1001101010010011010100011 6
b1001101010010011010100011 >
b100001 4
b100001 7
#69
13
#70
b1111 #
b1111 H
b1111 R
b1100 &
b1100 B
b1100 K
b1111 M
b1111 1
b1111 L
b1111 P
b1100 +
b1100 ?
b1100 @
b1100 C
b1 -
b1 A
b1 E
b1 N
b11110 G
b11 2
b11 D
b11 I
b10010 F
03
b100011 5
b1111010010010011000100011 *
b1111010010010011000100011 6
b1111010010010011000100011 >
b100010 4
b100010 7
#71
13
#72
b110 #
b110 H
b110 R
b1010 &
b1010 B
b1010 K
b1100 M
b110 %
b110 O
b110 Q
b1100 1
b1100 L
b1100 P
0'
1)
1$
1(
b1010 +
b1010 ?
b1010 @
b101 C
b1010 G
b10 2
b10 D
b10 I
b1011 F
b11 8
03
b100100 5
b101001011010001010000011 *
b101001011010001010000011 6
b101001011010001010000011 >
b100011 4
b100011 7
#73
13
#74
b10 #
b10 H
b10 R
b10 %
b10 O
b10 Q
b1101 M
b1101 1
b1101 L
b1101 P
b110 C
b11 2
b11 D
b11 I
b1100 F
03
b100101 5
b101001100010001100000011 *
b101001100010001100000011 6
b101001100010001100000011 >
b100100 4
b100100 7
#75
13
