Khizar/verilog/single-cycle/onlyclock/datamemory.v
module datamemory(clk, address, writedata, memread, memwrite, readdata);

    input clk;
    input memread, memwrite;
    input [31:0] writedata;
    input [9:0] address; // change later
    
    output wire [31:0] readdata;

    reg [7:0] memfile [0:1023]; // increase memory size later

    assign readdata = (memread == 1) ? {memfile[address+3], memfile[address+2], memfile[address+1], memfile[address]} : 0;

    always @ (posedge clk)
        begin
            if (memwrite == 1)
                {memfile[address+3], memfile[address+2], memfile[address+1], memfile[address]} <= writedata;
        end

endmodule

Khizar/verilog/single-cycle/old/withclock/datamemory_tb.v
`include "datamemory.v"

module datamemory_tb;//(address, writedata, memread, memwrite, readdata);

    reg clk;
    reg memread, memwrite;
    reg [31:0] writedata;
    reg [9:0] address;
    
    wire [31:0] readdata;

    datamemory   uut(clk, address, writedata, memread, memwrite, readdata);

    always #1 clk = ~clk;

    initial 
        begin
            $dumpfile("../vcd/datamemory_tb.vcd");
            $dumpvars(2, datamemory_tb);

            clk = 0;

            #3
            memread     = 0;
            memwrite    = 1;
            address     = 10'b00_0000_0000;

            #3
            writedata   = 32'b1100_0000_0000_0000_0000_0000_1111_0000;

            #3
            address     = 10'b00_0000_0001;

            #3
            writedata   = 32'b0000_0000_0000_0000_0000_1111_0000_0000;

            #3
            address     = 10'b00_0000_0010;

            #3
            writedata   = 32'b0000_0000_0000_0000_1111_0000_0000_0000;

            #3
            address     = 10'b00_0000_0011;

            #3
            writedata   = 32'b0000_0000_0000_1111_0000_0000_0000_0000;

            #3
            address     = 10'b01_0100_0101;

            #3
            writedata   = 32'b1111_0000_0000_0000_0000_1111_0000_0000;

            #3
            address     = 10'b11_0000_0101;

            #3
            writedata   = 32'b1001_0000_0110_0000_0000_1111_0000_0000;

            #3
            address     = 10'b10_1110_0000;

            #3
            writedata   = 32'b1100_0111_0000_0011_0000_1111_0000_0000;

            #3
            memread     = 1;
            memwrite    = 0;

            #3
            address     = 10'b00_0000_0000;

            #3
            $display("readdata: %d", readdata);

            #3
            address     = 10'b00_0000_0001;

            #3
            $display("readdata: %d", readdata);

            #3
            address     = 10'b00_0000_0010;

            #3
            $display("readdata: %d", readdata);

            #3
            address     = 10'b00_0000_0011;

            #3
            $display("readdata: %d", readdata);

            #3
            address     = 10'b01_0100_0101;

            #3
            $display("readdata: %d", readdata);

            #3
            address     = 10'b11_0000_0101;

            #3
            $display("readdata: %d", readdata);

            #3
            address     = 10'b10_1110_0000;

            #3
            $display("readdata: %d", readdata);

            $finish;
        end



endmodule

Khizar/verilog/single-cycle/vcd/datamemory_tb.vcd
$date
	Mon Jul 17 11:12:49 2023
$end
$version
	Icarus Verilog
$end
$timescale
	1s
$end
$scope module datamemory_tb $end
$var wire 32 ! readdata [31:0] $end
$var reg 10 " address [9:0] $end
$var reg 1 # clk $end
$var reg 1 $ memread $end
$var reg 1 % memwrite $end
$var reg 32 & writedata [31:0] $end
$scope module uut $end
$var wire 10 ' address [9:0] $end
$var wire 1 # clk $end
$var wire 1 $ memread $end
$var wire 1 % memwrite $end
$var wire 32 ( writedata [31:0] $end
$var reg 32 ) readdata [31:0] $end
$upscope $end
$upscope $end
$enddefinitions $end
#0
$dumpvars
bx )
bx (
bx '
bx &
x%
x$
0#
bx "
bx !
$end
#1
1#
#2
0#
#3
1#
b0 "
b0 '
1%
0$
#4
0#
#5
1#
#6
0#
b11000000000000000000000011110000 &
b11000000000000000000000011110000 (
#7
1#
#8
0#
#9
1#
b1 "
b1 '
#10
0#
#11
1#
#12
0#
b111100000000 &
b111100000000 (
#13
1#
#14
0#
#15
1#
b10 "
b10 '
#16
0#
#17
1#
#18
0#
b1111000000000000 &
b1111000000000000 (
#19
1#
#20
0#
#21
1#
b11 "
b11 '
#22
0#
#23
1#
#24
0#
b11110000000000000000 &
b11110000000000000000 (
#25
1#
#26
0#
#27
1#
b101000101 "
b101000101 '
#28
0#
#29
1#
#30
0#
b11110000000000000000111100000000 &
b11110000000000000000111100000000 (
#31
1#
#32
0#
#33
1#
b1100000101 "
b1100000101 '
#34
0#
#35
1#
#36
0#
b10010000011000000000111100000000 &
b10010000011000000000111100000000 (
#37
1#
#38
0#
#39
1#
b1011100000 "
b1011100000 '
#40
0#
#41
1#
#42
0#
b11000111000000110000111100000000 &
b11000111000000110000111100000000 (
#43
1#
#44
0#
#45
b11000111000000110000111100000000 !
b11000111000000110000111100000000 )
1#
0%
1$
#46
0#
#47
1#
#48
b11000000000000000000000011110000 !
b11000000000000000000000011110000 )
0#
b0 "
b0 '
#49
1#
#50
0#
#51
1#
#52
0#
#53
1#
#54
b111100000000 !
b111100000000 )
0#
b1 "
b1 '
#55
1#
#56
0#
#57
1#
#58
0#
#59
1#
#60
b1111000000000000 !
b1111000000000000 )
0#
b10 "
b10 '
#61
1#
#62
0#
#63
1#
#64
0#
#65
1#
#66
b11110000000000000000 !
b11110000000000000000 )
0#
b11 "
b11 '
#67
1#
#68
0#
#69
1#
#70
0#
#71
1#
#72
b11110000000000000000111100000000 !
b11110000000000000000111100000000 )
0#
b101000101 "
b101000101 '
#73
1#
#74
0#
#75
1#
#76
0#
#77
1#
#78
b10010000011000000000111100000000 !
b10010000011000000000111100000000 )
0#
b1100000101 "
b1100000101 '
#79
1#
#80
0#
#81
1#
#82
0#
#83
1#
#84
b11000111000000110000111100000000 !
b11000111000000110000111100000000 )
0#
b1011100000 "
b1011100000 '
