Khizar/verilog/single-cycle/onlyclock/mux2_1.v
module mux2_1(in1, in2, s, out);

    input [31:0] in1, in2;
    input s;

    output reg [31:0] out;

    always @ (in1, in2, s)
        begin
            if (s == 0)
                out <= in1;
            else
                out <= in2;
        end

endmodule

Khizar/verilog/single-cycle/onlyclock/datamemory.v
module datamemory(clk, address, writedata, memread, memwrite, readdata);

    input clk;
    input memread, memwrite;
    input [31:0] writedata;
    input [9:0] address; // change later
    
    output wire [31:0] readdata;

    reg [7:0] memfile [0:1023]; // increase memory size later

    assign readdata = (memread == 1) ? {memfile[address+3], memfile[address+2], memfile[address+1], memfile[address]} : 0;

    always @ (posedge clk)
        begin
            if (memwrite == 1)
                {memfile[address+3], memfile[address+2], memfile[address+1], memfile[address]} <= writedata;
        end

endmodule

Khizar/verilog/singleImplem/alu.v
module alu(aluctl, a, b, out, zero, overflow);

    input [3:0] aluctl; 

    input [31:0] a;
    input [31:0] b;

    output reg [31:0] out;
    output zero, overflow;

    assign zero = (out == 0);

    always @ (aluctl, a, b)
        begin
            case (aluctl)
                0: out <= a & b;
                1: out <= a | b;
                2: out <= a + b;
                6: out <= a - b;
                7: out <= (a < b ? 1: 0);
                12: out <= ~(a | b);
                default: out <= 0;
            endcase
        end

endmodule

Khizar/verilog/single-cycle/old/alucontrol.v
module alucontrol(aluop, func7, func3, aluctl);

    input [1:0] aluop;
    input [6:0] func7;
    input [2:0] func3;

    output reg [3:0] aluctl;

    always @ (aluop, func7, func3)
        begin
          if (aluop == 2'b00)
            aluctl <= 4'b0010;
          else if (aluop == 2'b01) 
            aluctl <= 4'b0110;
          else if (aluop == 2'b10)
            begin
              if (func7 == 7'b0000000)
                begin
                  if (func3 == 3'b000)
                    aluctl <= 4'b0010;
                  else if (func3 == 3'b111)
                    aluctl <= 4'b0000;
                  else if (func3 == 3'b100)
                    aluctl <= 4'b1100;
                  else if (func3 == 3'b110)
                    aluctl <= 4'b0001;
                end
              else if (func7 == 7'b0100000)
                begin
                  if (func3 == 3'b000)
                    aluctl <= 4'b0110;
                end
            end
        end

endmodule

Khizar/verilog/single-cycle/onlyclock/immediategen.v
module immediategen(instruction, result);

    input [31:0] instruction;

    output reg [31:0] result;

    always @ (instruction)
        begin
            case (instruction[6:0])
                7'b0000011, 7'b0010011: result <= {{20{instruction[31]}}, instruction[31:20]};
                7'b0100011: result <= {{19{instruction[31]}}, instruction[31:25], instruction[11:7]};
                7'b1100011: result <= {{18{instruction[31]}}, instruction[31], instruction[7], instruction[30:25], instruction[11:8], 1'b0};
                    
                default: result <= 5;
            endcase
        end

endmodule

Khizar/verilog/single-cycle/riscv-single-cycle/registerfile.v
module registerfile(clk, rs1, rs2, rd, writedata, regwrite, readdata1, readdata2);

    input clk;
    input [4:0] rs1, rs2, rd;
    input [31:0] writedata;
    input regwrite;

    output wire [31:0] readdata1, readdata2;

    reg [31:0] regfile [0:31];

    initial 
      begin
        regfile[0] <= 0;    
      end

    assign readdata1 = regfile[rs1];
    assign readdata2 = regfile[rs2];

    always @ (posedge clk)
        begin
          if (regwrite == 1 & rd != 0)
              regfile[rd] <= writedata;          
        end

endmodule

Khizar/verilog/single-cycle/onlyclock/maincontrol.v
module maincontrol(clk, instruction, branch, memread, memtoreg, aluop, memwrite, alusrc, regwrite);

    input clk;
    input [6:0] instruction;

    output reg branch, memread, memtoreg, memwrite, alusrc, regwrite;
    output reg [1:0] aluop;

    always @ (instruction)
        begin
          case (instruction)
            7'b0110011: 
              begin
                alusrc <= 0;
                memtoreg <= 0;
                regwrite <= 1;
                memread <= 0;
                memwrite <= 0;
                branch <= 0;
                aluop <= 2'b10;
              end
            7'b0000011: 
              begin
                alusrc <= 1;
                memtoreg <= 1;
                regwrite <= 1;
                memread <= 1;
                memwrite <= 0;
                branch <= 0;
                aluop <= 2'b00;
              end
            7'b0100011:
              begin
                alusrc <= 1;
                regwrite <= 0;
                memread <= 0;
                memwrite <= 1;
                branch <= 0;
                aluop <= 2'b00;
              end
            7'b1100011: 
              begin
                alusrc <= 0;
                regwrite <= 0;
                memread <= 0;
                memwrite <= 0;
                branch <= 1;
                aluop <= 2'b01;
              end
            7'b0010011: // for addi (i-type)
              begin
                alusrc <= 1;
                regwrite <= 1;
                memtoreg <= 0;
                memread <= 0;
                memwrite <= 0;
                branch <= 0;
                aluop <= 2'b00;
              end

            default: 
              begin
                alusrc <= 0;
                regwrite <= 0;
                memread <= 0;
                memwrite <= 0;
                memtoreg <= 0;
                branch <= 0;
                aluop <= 2'b00;
              end
          endcase
        end

endmodule

Khizar/verilog/single-cycle/onlyclock/instructionmemory.v
module instructionmemory(clk, pc, instruction);

    input clk;
    input [9:0] pc; // change later
    
    output wire [31:0] instruction;

    reg [7:0] memfile [0:1023]; // increase memory size later

    initial
        begin // write instructions here
            // x0 = 0 already done

            //  addi x10, x0,  1     
            {memfile[3], memfile[2], memfile[1], memfile[0]} <= 32'b0000_0000_0001___00000___000___0101______0___001_0011;          //  x10     =   1

            //  addi x11, x10, 1
            memfile[1] <= 32'b0000_0000_0001___01010___000___01011___001_0011;          //  x11     =   2

            //  addi x12, x10, 2
            memfile[2] <= 32'b0000_0000_0010___01010___000___01100___001_0011;          //  x12     =   3
            
            //  nop
            memfile[3] <= 32'b0000_0000_0000___00000___000___00000___000_0000;          //  nop
            
            //  sw   x10, 9(x0)
            memfile[4]  <= 32'b0000000___01010___00000___010___01001___010_0011;        //  mem[9]  =   1

            //  nop
            memfile[5] <= 32'b0000_0000_0000___00000___000___00000___000_0000;          //  nop
            
            //  addi x13, x10, 3 
            memfile[6] <= 32'b0000_0000_0011___01010___000___01101___001_0011;          //  x13     =   4

            //  add  x14, x13, x11 (rd, rs1, rs2)                                                                                               
            memfile[7] <= 32'b0000000___01011___01101___000___01110___011_0011;         //  x14     =   6   (x14 = x11 + x13)

            //  addi x15, x14, 0
            memfile[8] <= 32'b0000_0000_0000___01110___000___01111___001_0011;          //  x15     =   6   (x15 = x14 + 0)

            //  sub x16, x15, x11
            memfile[9] <= 32'b0100000___01011___01111___000___10000___011_0011;          // x16     =   4   (x16 = x15 - x11)
                
            //  addi x17, x16, 0
            memfile[10] <= 32'b0000_0000_0000___10000___000___10001___001_0011;          //  x17     =   4   (x17 = x16 + 0)

            //  sw   x11, 4(x0)         
            memfile[11]  <= 32'b0000000___01011___00000___010___00100___010_0011;         //  mem[4]  =   2

            //  nop
            memfile[12] <= 32'b0000_0000_0000___00000___000___00000___000_0000;         //  nop

            //  sw   x12, 5(x0)         
            memfile[13] <= 32'b0000000___01100___00000___010___00101___010_0011;         // mem[5]  =   3

            //  nop
            memfile[14] <= 32'b0000_0000_0000___00000___000___00000___000_0000;         //  nop

            //  lw   x18, 5(x0)         
            memfile[15] <= 32'b0000_0000_0101___00000___010___10010___000_0011;         //  x18     =   mem[5]  =   3
            
            //  nop
            memfile[16] <= 32'b0000_0000_0000___00000___000___00000___000_0000;         //  nop

            //  addi x19, x18, 0
            memfile[17] <= 32'b0000_0000_0000___10010___000___10011___001_0011;          //  x19     =   3   (x19 = x18 + 0)

            //  and  x20, x10, x18                                                                                               
            memfile[18] <= 32'b0000000___01010___10010___111___10100___011_0011;         //  x20     =   1   (x20 = x10 & x18)
            //  x10 = 0000_0000_0000_0000_0000_0000_0000_0001
            //  x18 = 0000_0000_0000_0000_0000_0000_0000_0011
            //  x20 = 0000_0000_0000_0000_0000_0000_0000_0001

            //  addi x23, x20, 0
            memfile[19] <= 32'b0000_0000_0000___10100___000___10111___001_0011;          //  x23     =   1   (x23 = x20 + 0)

            //  or  x21, x11, x16                                                                                               
            memfile[20] <= 32'b0000000___01011___10000___110___10101___011_0011;         //  x21     =   6   (x21 = x11 | x16)
            //  x11 = 0000_0000_0000_0000_0000_0000_0000_0010
            //  x16 = 0000_0000_0000_0000_0000_0000_0000_0100
            //  x21 = 0000_0000_0000_0000_0000_0000_0000_0110

            //  addi x24, x21, 0
            memfile[21] <= 32'b0000_0000_0000___10101___000___11000___001_0011;          //  x24     =   6   (x24 = x21 + 0)

            // xor  x22, x14, x17                                                                                               
            memfile[22] <= 32'b0000000___01110___10001___100___10110___011_0011;         //  x22     =   2   (x22 = x14 xor x17)
            //  x14 = 0000_0000_0000_0000_0000_0000_0000_0110
            //  x17 = 0000_0000_0000_0000_0000_0000_0000_0100
            //  x22 = 0000_0000_0000_0000_0000_0000_0000_0010

            //  addi x25, x22, 0
            memfile[23] <= 32'b0000_0000_0000___10110___000___11001___001_0011;          //  x25     =   2   (x25 = x22 + 0)

            //  nop
            memfile[24] <= 32'b0000_0000_0000___00000___000___00000___000_0000;         //  nop
            
            //  lw   x26, 4(x0)         
            memfile[25] <= 32'b0000_0000_0100___00000___010___11010___000_0011;         //  x26     =   mem[4]  = 2
                
            //  addi x27, x26, 0
            memfile[26] <= 32'b0000_0000_0000___11010___000___11011___001_0011;          //  x27     =   2   (x27 = x26 + 0)

            //  nop
            memfile[27] <= 32'b0000_0000_0000___00000___000___00000___000_0000;         //  nop

            //  lw   x30, 9(x0)         
            memfile[28] <= 32'b0000_0000_1001___00000___010___11110___000_0011;         //  x30     =   mem[9]  =   1
            //  nop
            memfile[29] <= 32'b0000_0000_0000___00000___000___00000___000_0000;         //  nop

            //  addi x31, x30, 0
            memfile[30] <= 32'b0000_0000_0000___11110___000___11111___001_0011;         //  x31     =   1

            //new test
            //  sw   x24, 8(x16)         
            memfile[31] <= 32'b0000000___11000___10000___010___01000___010_0011;        // mem[12]  =   6

            //  sw   x25, 9(x17)         
            memfile[32] <= 32'b0000000___11001___10001___010___01001___010_0011;        // mem[13]  =   2

            //  sw   x19, 13(x10)         
            memfile[33] <= 32'b0000000___10011___01010___010___01101___010_0011;        // mem[14]  =   3

            //  sw   x30, 12(x18)         
            memfile[34] <= 32'b0000000___11110___10010___010___01100___010_0011;        // mem[15]  =   1

            //  lw   x5, 10(x11)         
            memfile[35] <= 32'b0000000___01010___01011___010___00101___000_0011;        // x5   =   mem[12]  =   6

            //  lw   x6, 10(x12)         
            memfile[36] <= 32'b0000000___01010___01100___010___00110___000_0011;        // x6   =   mem[13]  =   2

            //  lw   x7, 8(x15)         
            memfile[37] <= 32'b0000000___01000___01111___010___00111___000_0011;        // x7   =   mem[14]  =   3

            //  lw   x8, 13(x25)         
            memfile[38] <= 32'b0000000___01101___11001___010___01000___000_0011;        // x8   =   mem[15]  =   1

            //  addi x4, x5, 0
            memfile[39] <= 32'b0000_0000_0000___00101___000___00100___001_0011;         //  x5     =   6
            
            //  addi x4, x6, 0
            memfile[40] <= 32'b0000_0000_0000___00110___000___00100___001_0011;         //  x6     =   2

            //  addi x4, x7, 0
            memfile[41] <= 32'b0000_0000_0000___00111___000___00100___001_0011;         //  x7     =   3

            //  addi x4, x8, 0
            memfile[42] <= 32'b0000_0000_0000___01000___000___00100___001_0011;         //  x8     =   1

        end

    
    assign instruction = {memfile[pc+3], memfile[pc+2], memfile[pc+1], memfile[pc]};


    //        ins[7:0]
    //        ins[15:0]
    //        .....
    //        ....

endmodule

Khizar/verilog/single-cycle/riscv-single-cycle/riscv.v
`include "maincontrol.v"
`include "alucontrol.v"
`include "alu.v"
`include "registerfile.v"
`include "instructionmemory.v"
`include "adder.v"
`include "datamemory.v"
`include "immediategen.v"
`include "mux2_1.v"

module combined_tb;

    reg [9:0] pc;
    reg clk;
    reg [1:0] state;
    reg select;

    wire branch, memread, memtoreg, memwrite, alusrc, regwrite, zero;
    wire [1:0] aluop;
    wire [3:0] aluctl;
    wire [31:0] instruction, a, b, immediate, mux_out, alu_out, writedata, readdata, sumA, sumB;

    instructionmemory   uutA(clk, pc, instruction);
    maincontrol         uutB(state, instruction[6:0], branch, memread, memtoreg, aluop, memwrite, alusrc, regwrite);
    registerfile        uutF(clk, instruction[19:15], instruction[24:20], instruction[11:7], writedata, regwrite, a, b);
    immediategen        uutD(instruction, immediate);
    alucontrol          uutC(aluop, instruction[31:25], instruction[14:12], aluctl);                   
    mux2_1              uutE(b, immediate, alusrc, mux_out);
    alu                 uutG(aluctl, a, mux_out, alu_out, zero, overflow);
    datamemory          uutH(clk, alu_out[9:0], b, memread, memwrite, readdata); // decreased address to 10 bits, change later
    mux2_1              uutI(alu_out, readdata, memtoreg, writedata);

    //adder               uutJ(pc, 1, pc);
    // adder               uutK(immediate, pc, sumB);
    //mux2_1              uutL(pc, sumB, select, newpc);

    integer i;

    always #1 clk = ~clk;

    always @(posedge clk) 
        begin
            if (state == 0)
                begin
                    //immediate = ins[7], ins[25:30]
                    pc = (branch & zero) ?  pc+immediate : pc+1;
                    state = state + 1;        
                end
            else if (state == 5)
                begin
                    state = 0;
                end
            else
                state = state + 1;
        end

    initial
        begin
            $dumpfile("../vcd/tb_automate_pc_1.vcd");
            $dumpvars(2, combined_tb);

            pc = -1;
            clk = 0;
            state = 0;

            #400 $finish;
        end

endmodule

Khizar/verilog/single-cycle/vcd/tb_automate_pc.vcd
$date
	Fri Jul 21 19:52:48 2023
$end
$version
	Icarus Verilog
$end
$timescale
	1s
$end
$scope module combined_tb $end
$var wire 1 ! overflow $end
$var wire 1 " zero $end
$var wire 32 # writedata [31:0] $end
$var wire 1 $ regwrite $end
$var wire 32 % readdata [31:0] $end
$var wire 32 & mux_out [31:0] $end
$var wire 1 ' memwrite $end
$var wire 1 ( memtoreg $end
$var wire 1 ) memread $end
$var wire 32 * instruction [31:0] $end
$var wire 32 + immediate [31:0] $end
$var wire 1 , branch $end
$var wire 32 - b [31:0] $end
$var wire 1 . alusrc $end
$var wire 2 / aluop [1:0] $end
$var wire 4 0 aluctl [3:0] $end
$var wire 32 1 alu_out [31:0] $end
$var wire 32 2 a [31:0] $end
$var reg 1 3 clk $end
$var reg 10 4 pc [9:0] $end
$var reg 2 5 state [1:0] $end
$var integer 32 6 i [31:0] $end
$scope module uutA $end
$var wire 1 3 clk $end
$var wire 10 7 pc [9:0] $end
$var reg 32 8 instruction [31:0] $end
$upscope $end
$scope module uutB $end
$var wire 1 3 clk $end
$var wire 7 9 instruction [6:0] $end
$var reg 2 : aluop [1:0] $end
$var reg 1 . alusrc $end
$var reg 1 , branch $end
$var reg 1 ) memread $end
$var reg 1 ( memtoreg $end
$var reg 1 ' memwrite $end
$var reg 1 $ regwrite $end
$upscope $end
$scope module uutC $end
$var wire 2 ; aluop [1:0] $end
$var wire 3 < func3 [2:0] $end
$var wire 7 = func7 [6:0] $end
$var reg 4 > aluctl [3:0] $end
$upscope $end
$scope module uutD $end
$var wire 32 ? instruction [31:0] $end
$var reg 32 @ result [31:0] $end
$upscope $end
$scope module uutE $end
$var wire 32 A in2 [31:0] $end
$var wire 1 . s $end
$var wire 32 B in1 [31:0] $end
$var reg 32 C out [31:0] $end
$upscope $end
$scope module uutF $end
$var wire 1 3 clk $end
$var wire 5 D rd [4:0] $end
$var wire 1 $ regwrite $end
$var wire 5 E rs1 [4:0] $end
$var wire 5 F rs2 [4:0] $end
$var wire 32 G writedata [31:0] $end
$var reg 32 H readdata1 [31:0] $end
$var reg 32 I readdata2 [31:0] $end
$upscope $end
$scope module uutG $end
$var wire 32 J a [31:0] $end
$var wire 4 K aluctl [3:0] $end
$var wire 32 L b [31:0] $end
$var wire 1 ! overflow $end
$var wire 1 " zero $end
$var reg 32 M out [31:0] $end
$upscope $end
$scope module uutH $end
$var wire 10 N address [9:0] $end
$var wire 1 3 clk $end
$var wire 1 ) memread $end
$var wire 1 ' memwrite $end
$var wire 32 O writedata [31:0] $end
$var reg 32 P readdata [31:0] $end
$upscope $end
$scope module uutI $end
$var wire 32 Q in1 [31:0] $end
$var wire 32 R in2 [31:0] $end
$var wire 1 ( s $end
$var reg 32 S out [31:0] $end
$upscope $end
$upscope $end
$enddefinitions $end
#0
$dumpvars
bx S
bx R
bx Q
bx P
bx O
bx N
bx M
bx L
bx K
bx J
bx I
bx H
bx G
bx F
bx E
bx D
bx C
bx B
bx A
bx @
bx ?
bx >
bx =
bx <
bx ;
bx :
bx 9
bx 8
b1111111111 7
b101100 6
b0 5
b1111111111 4
03
bx 2
bx 1
bx 0
bx /
x.
bx -
x,
bx +
bx *
x)
x(
x'
bx &
bx %
x$
bx #
x"
z!
$end
#1
b1 +
b1 @
b1 A
b10 0
b10 >
b10 K
b0 <
b0 =
b1010 D
b1 F
b0 E
b10011 9
b100000000010100010011 *
b100000000010100010011 8
b100000000010100010011 ?
b0 /
b0 :
b0 ;
0,
0(
0'
0)
0$
0.
b1 5
b0 4
b0 7
13
#2
03
#3
b1 #
b1 G
b1 S
b1 N
0"
b1 1
b1 M
b1 Q
b1 &
b1 C
b1 L
b0 2
b0 H
b0 J
1$
1.
b10 5
13
#4
03
#5
b0 5
13
#6
03
#7
b1 5
b1 4
b1 7
13
#8
03
#9
b1011 D
b1010 E
b101010000010110010011 *
b101010000010110010011 8
b101010000010110010011 ?
b10 5
13
#10
03
#11
b10 #
b10 G
b10 S
b10 N
b10 1
b10 M
b10 Q
b1 2
b1 H
b1 J
b0 5
13
#12
03
#13
b11 #
b11 G
b11 S
b11 N
b11 1
b11 M
b11 Q
b10 &
b10 C
b10 L
b10 +
b10 @
b10 A
b1100 D
b10 F
b1001010000011000010011 *
b1001010000011000010011 8
b1001010000011000010011 ?
b1 5
b10 4
b10 7
13
#14
03
#15
b10 5
13
#16
03
#17
b0 5
13
#18
03
#19
b1 5
b11 4
b11 7
13
#20
03
#21
b1 #
b1 G
b1 S
b1 N
b1 1
b1 M
b1 Q
b0 &
b0 C
b0 L
b0 +
b0 @
b0 A
b0 D
b0 F
b0 E
b0 9
b0 *
b0 8
b0 ?
b10 5
13
#22
03
#23
b0 #
b0 G
b0 S
b0 N
1"
b0 1
b0 M
b0 Q
b0 -
b0 B
b0 I
b0 O
b0 2
b0 H
b0 J
0$
0.
b0 5
13
#24
03
#25
b1001 +
b1001 @
b1001 A
b10 <
b1001 D
b1010 F
b100011 9
b101000000010010010100011 *
b101000000010010010100011 8
b101000000010010010100011 ?
b1 5
b100 4
b100 7
13
#26
03
#27
b1001 #
b1001 G
b1001 S
b1001 N
0"
b1001 1
b1001 M
b1001 Q
b1001 &
b1001 C
b1001 L
b1 -
b1 B
b1 I
b1 O
1'
1.
b10 5
13
#28
03
#29
b0 5
13
#30
03
#31
b1 5
b101 4
b101 7
13
#32
03
#33
b0 #
b0 G
b0 S
b0 N
1"
b0 1
b0 M
b0 Q
b0 &
b0 C
b0 L
b0 +
b0 @
b0 A
b0 <
b0 D
b0 F
b0 9
b0 *
b0 8
b0 ?
b10 5
13
#34
03
#35
b0 -
b0 B
b0 I
b0 O
0'
0.
b0 5
13
#36
03
#37
b11 +
b11 @
b11 A
b1101 D
b11 F
b1010 E
b10011 9
b1101010000011010010011 *
b1101010000011010010011 8
b1101010000011010010011 ?
b1 5
b110 4
b110 7
13
#38
03
#39
b100 #
b100 G
b100 S
b100 N
0"
b100 1
b100 M
b100 Q
b11 &
b11 C
b11 L
bx -
bx B
bx I
bx O
b1 2
b1 H
b1 J
1$
1.
b10 5
13
#40
03
#41
b0 5
13
#42
03
#43
b1 5
b111 4
b111 7
13
#44
03
#45
b1 #
b1 G
b1 S
b1 N
b1 1
b1 M
b1 Q
b0 &
b0 C
b0 L
b0 +
b0 @
b0 A
b1110 D
b1011 F
b1101 E
b110011 9
b101101101000011100110011 *
b101101101000011100110011 8
b101101101000011100110011 ?
b10 5
13
#46
03
#47
b110 #
b110 G
b110 S
b110 N
b110 1
b110 M
b110 Q
b10 &
b10 C
b10 L
b10 -
b10 B
b10 I
b10 O
b100 2
b100 H
b100 J
b10 /
b10 :
b10 ;
0.
b0 5
13
#48
03
#49
b1111 D
b0 F
b1110 E
b10011 9
b1110000011110010011 *
b1110000011110010011 8
b1110000011110010011 ?
b1 5
b1000 4
b1000 7
13
