Khizar/verilog/single-cycle/datamemory.v
module datamemory(address, writedata, memread, memwrite, readdata);

    input memread, memwrite;
    input [31:0] writedata;
    input [9:0] address; // change later
    
    output reg [31:0] readdata;

    reg [31:0] memfile [0:1023]; // increase memory size later

    always @ (address, writedata, memread, memwrite)
        begin
            if (memwrite == 1)
                memfile[address] <= writedata;
            else if (memread == 1)
                readdata <= memfile[address];
        end

endmodule

Khizar/verilog/singleImplem/datamemory_tb.v
`include "datamemory.v"

module datamemory_tb;//(address, writedata, memread, memwrite, readdata);

    reg memread, memwrite;
    reg [31:0] writedata;
    reg [9:0] address;
    
    wire [31:0] readdata;

    datamemory   uut(address, writedata, memread, memwrite, readdata);

    initial 
        begin
            $dumpfile("datamemory_tb.vcd");
            $dumpvars(2, datamemory_tb);

            #1
            memread     = 0;
            memwrite    = 1;
            address     = 10'b00_0000_0000;

            #1
            writedata   = 32'b1100_0000_0000_0000_0000_0000_1111_0000;

            #1
            address     = 10'b00_0000_0001;

            #1
            writedata   = 32'b0000_0000_0000_0000_0000_1111_0000_0000;

            #1
            address     = 10'b00_0000_0010;

            #1
            writedata   = 32'b0000_0000_0000_0000_1111_0000_0000_0000;

            #1
            address     = 10'b00_0000_0011;

            #1
            writedata   = 32'b0000_0000_0000_1111_0000_0000_0000_0000;

            #1
            address     = 10'b01_0100_0101;

            #1
            writedata   = 32'b1111_0000_0000_0000_0000_1111_0000_0000;

            #1
            address     = 10'b11_0000_0101;

            #1
            writedata   = 32'b1001_0000_0110_0000_0000_1111_0000_0000;

            #1
            address     = 10'b10_1110_0000;

            #1
            writedata   = 32'b1100_0111_0000_0011_0000_1111_0000_0000;

            #1
            memread     = 1;
            memwrite    = 0;

            #1
            address     = 10'b00_0000_0000;

            #1
            $display("readdata: %d", readdata);

            #1
            address     = 10'b00_0000_0001;

            #1
            $display("readdata: %d", readdata);

            #1
            address     = 10'b00_0000_0010;

            #1
            $display("readdata: %d", readdata);

            #1
            address     = 10'b00_0000_0011;

            #1
            $display("readdata: %d", readdata);

            #1
            address     = 10'b01_0100_0101;

            #1
            $display("readdata: %d", readdata);

            #1
            address     = 10'b11_0000_0101;

            #1
            $display("readdata: %d", readdata);

            #1
            address     = 10'b10_1110_0000;

            #1
            $display("readdata: %d", readdata);

        end



endmodule

Khizar/verilog/singleImplem/datamemory_tb.vcd
$date
	Sat Jul 15 16:04:19 2023
$end
$version
	Icarus Verilog
$end
$timescale
	1s
$end
$scope module datamemory_tb $end
$var wire 32 ! readdata [31:0] $end
$var reg 10 " address [9:0] $end
$var reg 1 # memread $end
$var reg 1 $ memwrite $end
$var reg 32 % writedata [31:0] $end
$scope module uut $end
$var wire 10 & address [9:0] $end
$var wire 1 # memread $end
$var wire 1 $ memwrite $end
$var wire 32 ' writedata [31:0] $end
$var reg 32 ( readdata [31:0] $end
$upscope $end
$upscope $end
$enddefinitions $end
#0
$dumpvars
bx (
bx '
bx &
bx %
x$
x#
bx "
bx !
$end
#1
b0 "
b0 &
1$
0#
#2
b11000000000000000000000011110000 %
b11000000000000000000000011110000 '
#3
b1 "
b1 &
#4
b111100000000 %
b111100000000 '
#5
b10 "
b10 &
#6
b1111000000000000 %
b1111000000000000 '
#7
b11 "
b11 &
#8
b11110000000000000000 %
b11110000000000000000 '
#9
b101000101 "
b101000101 &
#10
b11110000000000000000111100000000 %
b11110000000000000000111100000000 '
#11
b1100000101 "
b1100000101 &
#12
b10010000011000000000111100000000 %
b10010000011000000000111100000000 '
#13
b1011100000 "
b1011100000 &
#14
b11000111000000110000111100000000 %
b11000111000000110000111100000000 '
#15
b11000111000000110000111100000000 !
b11000111000000110000111100000000 (
0$
1#
#16
b11000000000000000000000011110000 !
b11000000000000000000000011110000 (
b0 "
b0 &
#18
b111100000000 !
b111100000000 (
b1 "
b1 &
#20
b1111000000000000 !
b1111000000000000 (
b10 "
b10 &
#22
b11110000000000000000 !
b11110000000000000000 (
b11 "
b11 &
#24
b11110000000000000000111100000000 !
b11110000000000000000111100000000 (
b101000101 "
b101000101 &
#26
b10010000011000000000111100000000 !
b10010000011000000000111100000000 (
b1100000101 "
b1100000101 &
#28
b11000111000000110000111100000000 !
b11000111000000110000111100000000 (
b1011100000 "
b1011100000 &
