Khizar/verilog/singleImplem/registerfile.v
module registerfile(rs1, rs2, rd, writedata, regwrite, readdata1, readdata2);

    input [4:0] rs1, rs2, rd;
    input [31:0] writedata;
    input regwrite;

    output reg [31:0] readdata1, readdata2;

    reg [31:0] regfile [0:31];
    
    always @ (rs1, rs2, rd, writedata, regwrite)
        begin
          if (regwrite == 1) // rd = 0 shouldn't be written
            begin
              regfile[rd] <= writedata;
            end

          readdata1 <= regfile[rs1];
          readdata2 <= regfile[rs2];

        end

endmodule

Khizar/verilog/singleImplem/alu.v
module alu(aluctl, a, b, out, zero);

    input [3:0] aluctl;

    input [31:0] a;
    input [31:0] b;

    output reg [31:0] out; // see overflow
    output zero;

    assign zero = (out == 0);

    always @ (aluctl, a, b)
        begin
            case (aluctl)
                0: out <= a & b;
                1: out <= a | b;
                2: out <= a + b;
                6: out <= a - b;
                7: out <= (a < b ? 1: 0);
                12: out <= ~(a | b);
                default: out <= 0;
            endcase
        end

endmodule

Khizar/verilog/singleImplem/alu-control.v
module alucontrol(aluop, func7, func3, aluctl);

    input [1:0] aluop;
    input [6:0] func7;
    input [2:0] func3;

    output reg [3:0] aluctl;

    always @ (aluop, func7, func3)
        begin
          case ()
            32: op <= 2;
            34: op <= 6;
            36: op <= 0;
            37: op <= 1;
            default: op <= 15;
          endcase
        end





endmodule

Khizar/verilog/singleImplem/maincontrol.v
module maincontrol(instruction, branch, memread, memtoreg, aluop, memwrite, alusrc, regwrite);

    input [6:0] instruction;

    output reg branch, memread, memtoreg, memwrite, alusrc, regwrite;
    output reg [1:0] aluop;

    always @ (instruction)
        begin
          case (instruction)
            7'b0110011: 
              begin
                alusrc <= 0;
                memtoreg <= 0;
                regwrite <= 1;
                memread <= 0;
                memwrite <= 0;
                branch <= 0;
                aluop <= 2'b10;
              end
            7'b0000011: 
              begin
                alusrc <= 1;
                memtoreg <= 1;
                regwrite <= 1;
                memread <= 1;
                memwrite <= 0;
                branch <= 0;
                aluop <= 2'b00;
              end
            7'b0100011:
              begin
                alusrc <= 1;
                regwrite <= 0;
                memread <= 0;
                memwrite <= 1;
                branch <= 0;
                aluop <= 2'b00;
              end
            7'b1100011: 
              begin
                alusrc <= 0;
                regwrite <= 0;
                memread <= 0;
                memwrite <= 0;
                branch <= 1;
                aluop <= 2'b01;
              end

            default: 
              begin
                alusrc <= 0;
                regwrite <= 0;
                memread <= 0;
                memwrite <= 0;
                branch <= 0;
                aluop <= 2'b00;
              end
          endcase
        end

endmodule

Khizar/verilog/singleImplem/alu-tb.v
`include "maincontrol.v"
`include "alu-control.v"
`include "alu.v"
`include "registerfile.v"

module tb_alu;

reg [6:0] opcode;
reg [6:0] func7;
reg [2:0] func3;
reg [4:0] rs1, rs2, rd;
reg [31:0] instruction;

reg [31:0] writedata;

wire branch, memread, memtoreg, memwrite, alusrc, regwrite, zero;
wire [1:0] aluop;
wire [3:0] aluctl;
wire [31:0] a, b;
wire [31:0] out;

maincontrol  uutA(instruction[6:0], branch, memread, memtoreg, aluop, memwrite, alusrc, regwrite);
alucontrol   uutB(aluop, instruction[31:25], instruction[14:12], aluctl);
alu          uutC(aluctl, a, b, out, zero);
registerfile uutD(instruction[19:15], instruction[24:20], instruction[11:7], writedata, regwrite, a, b);

initial 
    begin
        rs1           = 5'b00000;
        rs2           = 5'b00000;
        rd            = 5'b00000;
        opcode        = 7'b0110011;
        func7         = 7'b0000000;
        func3         = 3'b000;

        instruction = {func7, rs2, rs1, func3, rd, opcode};
    end

initial
    begin
        $dumpfile("myalu.vcd");
        $dumpvars(2, tb_alu);

        //initialize some registers
        #1
        rd            = 5'b00000;
        instruction = {func7, rs2, rs1, func3, rd, opcode};

        #1
        writedata     = {{28{1'b0}}, 4'b0000};

        #1 // x1 = 1
        rd            = 5'b00001;
        instruction = {func7, rs2, rs1, func3, rd, opcode};

        #1
        writedata     = {{28{1'b0}}, 4'b0001};

        #1 // x2 = 2
        rd            = 5'b00010;
        instruction = {func7, rs2, rs1, func3, rd, opcode};
        
        #1
        writedata     = {{28{1'b0}}, 4'b0010};

        #1 // x3 = 3
        rd            = 5'b00011;
        instruction = {func7, rs2, rs1, func3, rd, opcode};
        
        #1
        writedata     = {{28{1'b0}}, 4'b0011};

        #1 // x4 = 4
        rd            = 5'b00100;
        instruction = {func7, rs2, rs1, func3, rd, opcode};
        
        #1
        writedata     = {{28{1'b0}}, 4'b0100};
        
        #1 // x5 = 5
        rd            = 5'b00101;
        instruction = {func7, rs2, rs1, func3, rd, opcode};
        
        #1
        writedata     = {{28{1'b0}}, 4'b0101};
        
        #2
        rs1           = 5'b00000;
        instruction = {func7, rs2, rs1, func3, rd, opcode};

        $display("readdata1 x0: %d", a);

        #2
        rs1           = 5'b00001;
        instruction = {func7, rs2, rs1, func3, rd, opcode};

        $display("readdata1 x1: %d", a);

        #2
        rs1           = 5'b00010;
        instruction = {func7, rs2, rs1, func3, rd, opcode};

        $display("readdata1 x2: %d", a);

        #2
        rs1           = 5'b00011;
        instruction = {func7, rs2, rs1, func3, rd, opcode};

        $display("readdata1 x3: %d", a);

        #2
        rs1           = 5'b00100;
        instruction = {func7, rs2, rs1, func3, rd, opcode};

        $display("readdata1 x4: %d", a);

        #2
        rs1           = 5'b00000;
        rs2           = 5'b00001;
        opcode        = 7'b0110011;
        func7         = 7'b0000000;
        func3         = 3'b000;

        instruction = {func7, rs2, rs1, func3, rd, opcode};

        $display("out first: %d", out);

        #2
        rs1           = 5'b00001;
        rs2           = 5'b00010;
        opcode        = 7'b0110011;
        func7         = 7'b0000000;
        func3         = 3'b000;

        instruction = {func7, rs2, rs1, func3, rd, opcode};

        $display("out: %d", out);

        #2
        rs1           = 5'b00010;
        rs2           = 5'b00011;
        opcode        = 7'b0110011;
        func7         = 7'b0000000;
        func3         = 3'b000;

        instruction = {func7, rs2, rs1, func3, rd, opcode};

        $display("out: %d", out);

        #2
        rs1           = 5'b00011;
        rs2           = 5'b00100;
        opcode        = 7'b0110011;
        func7         = 7'b0000000;
        func3         = 3'b000;

        instruction = {func7, rs2, rs1, func3, rd, opcode};

        $display("out: %d", out);

        #2
        $display("out: %d", out);
    end

endmodule

Khizar/verilog/singleImplem/myalu.vcd
$date
	Wed Jul 12 23:01:02 2023
$end
$version
	Icarus Verilog
$end
$timescale
	1s
$end
$scope module tb_alu $end
$var wire 1 ! zero $end
$var wire 1 " regwrite $end
$var wire 32 # out [31:0] $end
$var wire 1 $ memwrite $end
$var wire 1 % memtoreg $end
$var wire 1 & memread $end
$var wire 1 ' branch $end
$var wire 32 ( b [31:0] $end
$var wire 1 ) alusrc $end
$var wire 2 * aluop [1:0] $end
$var wire 4 + aluctl [3:0] $end
$var wire 32 , a [31:0] $end
$var reg 3 - func3 [2:0] $end
$var reg 7 . func7 [6:0] $end
$var reg 32 / instruction [31:0] $end
$var reg 7 0 opcode [6:0] $end
$var reg 5 1 rd [4:0] $end
$var reg 5 2 rs1 [4:0] $end
$var reg 5 3 rs2 [4:0] $end
$var reg 32 4 writedata [31:0] $end
$scope module uutA $end
$var wire 7 5 instruction [6:0] $end
$var reg 2 6 aluop [1:0] $end
$var reg 1 ) alusrc $end
$var reg 1 ' branch $end
$var reg 1 & memread $end
$var reg 1 % memtoreg $end
$var reg 1 $ memwrite $end
$var reg 1 " regwrite $end
$upscope $end
$scope module uutB $end
$var wire 2 7 aluop [1:0] $end
$var wire 3 8 func3 [2:0] $end
$var wire 7 9 func7 [6:0] $end
$var reg 4 : aluctl [3:0] $end
$upscope $end
$scope module uutC $end
$var wire 4 ; aluctl [3:0] $end
$var wire 1 ! zero $end
$var wire 32 < b [31:0] $end
$var wire 32 = a [31:0] $end
$var reg 32 > out [31:0] $end
$upscope $end
$scope module uutD $end
$var wire 5 ? rd [4:0] $end
$var wire 1 " regwrite $end
$var wire 5 @ rs1 [4:0] $end
$var wire 5 A rs2 [4:0] $end
$var wire 32 B writedata [31:0] $end
$var reg 32 C readdata1 [31:0] $end
$var reg 32 D readdata2 [31:0] $end
$upscope $end
$upscope $end
$enddefinitions $end
#0
$dumpvars
bx D
bx C
bx B
b0 A
b0 @
b0 ?
bx >
bx =
bx <
b10 ;
b10 :
b0 9
b0 8
b10 7
b10 6
b110011 5
bx 4
b0 3
b0 2
b0 1
b110011 0
b110011 /
b0 .
b0 -
bx ,
b10 +
b10 *
0)
bx (
0'
0&
0%
0$
bx #
1"
x!
$end
#2
b0 4
b0 B
#3
1!
b0 #
b0 >
b0 (
b0 <
b0 D
b0 ,
b0 =
b0 C
b1 ?
b10110011 /
b1 1
#4
b1 4
b1 B
#5
b10 ?
b100110011 /
b10 1
#6
b10 4
b10 B
#7
b11 ?
b110110011 /
b11 1
#8
b11 4
b11 B
#9
b100 ?
b1000110011 /
b100 1
#10
b100 4
b100 B
#11
b101 ?
b1010110011 /
b101 1
#12
b101 4
b101 B
#16
0!
b1 #
b1 >
b1 ,
b1 =
b1 C
b1 @
b1000001010110011 /
b1 2
#18
b10 #
b10 >
b10 ,
b10 =
b10 C
b10 @
b10000001010110011 /
b10 2
#20
b11 #
b11 >
b11 ,
b11 =
b11 C
b11 @
b11000001010110011 /
b11 2
#22
b100 #
b100 >
b100 ,
b100 =
b100 C
b100 @
b100000001010110011 /
b100 2
#24
b1 #
b1 >
b1 (
b1 <
b1 D
b0 ,
b0 =
b0 C
b0 @
b1 A
b100000000001010110011 /
b1 3
b0 2
#26
b11 #
b11 >
b10 (
b10 <
b10 D
b1 ,
b1 =
b1 C
b1 @
b10 A
b1000001000001010110011 /
b10 3
b1 2
#28
b101 #
b101 >
b11 (
b11 <
b11 D
b10 ,
b10 =
b10 C
b10 @
b11 A
b1100010000001010110011 /
b11 3
b10 2
#30
b111 #
b111 >
b100 (
b100 <
b100 D
b11 ,
b11 =
b11 C
b11 @
b100 A
b10000011000001010110011 /
b100 3
b11 2
