Khizar/verilog/singleImplem/registerfile.v
module registerfile(rs1, rs2, rd, writedata, regwrite, readdata1, readdata2);

    input [4:0] rs1, rs2, rd;
    input [31:0] writedata;
    input regwrite;

    output reg [31:0] readdata1, readdata2;

    reg [31:0] regfile [0:31];
    
    always @ (rs1, rs2, rd, writedata, regwrite)
        begin
          if (regwrite == 1) // rd = 0 shouldn't be written
            begin
              regfile[rd] <= writedata;
            end

          readdata1 <= regfile[rs1];
          readdata2 <= regfile[rs2];

        end

endmodule

Khizar/verilog/singleImplem/registerfile_tb.v
`include "registerfile.v"

module registerfile_tb;

    reg [4:0] rs1, rs2, rd;
    reg [31:0] writedata;
    reg regwrite;
    wire [31:0] readdata1, readdata2;

    //rs1, rs2, rd, writedata, regwrite, readdata1, readdata2
    registerfile uut(rs1, rs2, rd, writedata, regwrite, readdata1, readdata2);

    //initialize some registers
    initial
        begin
            $dumpfile("registerfile_tb_dump.vcd");
            $dumpvars(1, registerfile_tb);

            #1
            regwrite = 1;

            #1 // x0 = 0
            rd            = 5'b00000;

            #1
            writedata     = {{28{1'b0}}, 4'b0000};

            #1 // x1 = 1
            rd            = 5'b00001;
            
            #1
            writedata     = {{28{1'b0}}, 4'b0001};

            #1 // x2 = 2
            rd            = 5'b00010;
                 
            #1
            writedata     = {{28{1'b0}}, 4'b0010};

            #1 // x3 = 3
            rd            = 5'b00011;
         
            #1
            writedata     = {{28{1'b0}}, 4'b0011};

            #1 // x4 = 4
            rd            = 5'b00100;
           
            #1
            writedata     = {{28{1'b0}}, 4'b0100};
            
            #1 // x5 = 5
            rd            = 5'b00101;
          
            #1
            writedata     = {{28{1'b0}}, 4'b0101};
            
            #1
            rs1           = 5'b00000;
            rs2           = 5'b00001;

            #1
            $display("x0: %d", readdata1);
            $display("x1: %d", readdata2);

            #1
            rs1           = 5'b00010;
            rs2           = 5'b00011;

            #1
            $display("x2: %d", readdata1);
            $display("x3: %d", readdata2);

            #1
            rs1           = 5'b00100;
            rs2           = 5'b00101;

            #1
            $display("x4: %d", readdata1);
            $display("x5: %d", readdata2);

            #1
            rs1           = 5'b00010;
            rs2           = 5'b00100;

            #1
            $display("x2: %d", readdata1);
            $display("x4: %d", readdata2);

            #1
            regwrite = 0;

            #1 // x0 = 0
            rd            = 5'b00001;

            #1
            writedata     = {{28{1'b0}}, 4'b0100};

            #1 // x0 = 0
            rd            = 5'b00011;

            #1
            writedata     = {{28{1'b0}}, 4'b0110};

            #1
            rs1           = 5'b00001;
            rs2           = 5'b00011;

            #1
            $display("x1: %d", readdata1);
            $display("x3: %d", readdata2);

        end



endmodule

Khizar/verilog/singleImplem/registerfile_tb_dump.vcd
$date
	Fri Jul 14 00:09:03 2023
$end
$version
	Icarus Verilog
$end
$timescale
	1s
$end
$scope module registerfile_tb $end
$var wire 32 ! readdata2 [31:0] $end
$var wire 32 " readdata1 [31:0] $end
$var reg 5 # rd [4:0] $end
$var reg 1 $ regwrite $end
$var reg 5 % rs1 [4:0] $end
$var reg 5 & rs2 [4:0] $end
$var reg 32 ' writedata [31:0] $end
$upscope $end
$enddefinitions $end
#0
$dumpvars
bx '
bx &
bx %
x$
bx #
bx "
bx !
$end
#1
1$
#2
b0 #
#3
b0 '
#4
b1 #
#5
b1 '
#6
b10 #
#7
b10 '
#8
b11 #
#9
b11 '
#10
b100 #
#11
b100 '
#12
b101 #
#13
b101 '
#14
b1 !
b0 "
b1 &
b0 %
#16
b11 !
b10 "
b11 &
b10 %
#18
b101 !
b100 "
b101 &
b100 %
#20
b100 !
b10 "
b100 &
b10 %
#22
0$
#23
b1 #
#24
b100 '
#25
b11 #
#26
b110 '
#27
b11 !
b1 "
b11 &
b1 %
