Khizar/verilog/singleImplem/instructionmemory.v
module instructionmemory(pc, instruction);

    input [9:0] pc; // change later
    
    output reg [31:0] instruction;

    reg [31:0] memfile [0:1023]; // increase memory size later

    initial
        begin // write instructions here
            // x0 = 0 already done

            //  addi x10, x0,  1
            //                immediate         rs1   func3   rd       opcode     
            memfile[0] <= 32'b0000_0000_0001___00000___000___01010___001_0011;          //  x10     =   1

            //  addi x11, x10, 1
            memfile[1] <= 32'b0000_0000_0001___01010___000___01011___001_0011;          //  x11     =   2

            //  addi x12, x10, 2
            memfile[2] <= 32'b0000_0000_0010___01010___000___01100___001_0011;          //  x12     =   3
              
            //  addi x13, x10, 3 
            memfile[3] <= 32'b0000_0000_0011___01010___000___01101___001_0011;          //  x13     =   4

            //  add  x14, x11, x13                                                                                               
            memfile[4] <= 32'b0000000___01011___01101___000___01110___011_0011;         //  x14     =   6   (x14 = x11 + x13)

            //  addi x15, x14, 0
            memfile[6] <= 32'b0000_0000_0000___01110___000___01111___001_0011;          //  x15     =   6   (x15 = x14 + 0)

            //  sub x16, x15, x11
            memfile[7] <= 32'b0100000___01011___01111___000___10000___011_0011;          // x16     =   4   (x16 = x15 - x11)
                
            //  addi x17, x16, 0
            memfile[8] <= 32'b0000_0000_0000___10000___000___10001___001_0011;          //  x17     =   4   (x17 = x16 + 0)

            //                0000000.  01011   00000   010   00100.  010 0011
            //  sw   x11, 4(x0)         
            memfile[9]  <= 32'b0000000___01011___00000___010___00100___010_0011;         //  mem[4]  =   2
            //                 
            //  sw   x12, 5(x0)         
            memfile[10] <= 32'b0000000___01100___00000___010___00101___010_0011;         // mem[5]  =   3

            //  lw   x18, 5(x0)         
            memfile[11] <= 32'b0000_0000_0101___00000___010___10010___000_0011;         //  x18     =   mem[5]  = 3
            //                 0000 0000 0101.  00000.  010.  10010.  000.0011
            //  addi x19, x18, 0
            memfile[12] <= 32'b0000_0000_0000___10010___000___10011___001_0011;          //  x19     =   3   (x19 = x18 + 0)

            //  and  x20, x10, x18                                                                                               
            memfile[13] <= 32'b0000000___01010___10010___111___10100___011_0011;         //  x20     =   1   (x20 = x10 & x18)
            //  x10 = 0000_0000_0000_0000_0000_0000_0000_0001
            //  x18 = 0000_0000_0000_0000_0000_0000_0000_0011
            //  x20 = 0000_0000_0000_0000_0000_0000_0000_0001

            //  addi x23, x20, 0
            memfile[14] <= 32'b0000_0000_0000___10100___000___10111___001_0011;          //  x23     =   1   (x23 = x20 + 0)

            //  or  x21, x11, x16                                                                                               
            memfile[15] <= 32'b0000000___01011___10000___110___10101___011_0011;         //  x21     =   6   (x21 = x11 | x16)
            //  x11 = 0000_0000_0000_0000_0000_0000_0000_0010
            //  x16 = 0000_0000_0000_0000_0000_0000_0000_0100
            //  x21 = 0000_0000_0000_0000_0000_0000_0000_0110

            //  addi x24, x21, 0
            memfile[16] <= 32'b0000_0000_0000___10101___000___11000___001_0011;          //  x24     =   6   (x24 = x21 + 0)

            // xor  x22, x14, x17                                                                                               
            memfile[17] <= 32'b0000000___01110___10001___100___10110___011_0011;         //  x22     =   2   (x22 = x14 xor x17)
            //  x14 = 0000_0000_0000_0000_0000_0000_0000_0110
            //  x17 = 0000_0000_0000_0000_0000_0000_0000_0100
            //  x22 = 0000_0000_0000_0000_0000_0000_0000_0010

            //  addi x25, x22, 0
            memfile[18] <= 32'b0000_0000_0000___10110___000___11001___001_0011;          //  x25     =   2   (x25 = x22 + 0)

            //  lw   x26, 4(x0)         
            memfile[19] <= 32'b0000_0000_0100___00000___010___11010___000_0011;         //  x26     =   mem[4]  = 2
//                             0000 0000 0100   00000   010   11010.  000 0011
            //  addi x27, x26, 0
            memfile[20] <= 32'b0000_0000_0000___11010___000___11011___001_0011;          //  x27     =   2   (x27 = x26 + 0)

            //  add  x14, x11, x13                                                                                               
            //memfile[15] <= 32'b0000000___01011___01101___000___01110___011_0011;         //  x14     =   6   (x14 = x11 + x13)

            //  addi x4, x3, 1
            //memfile[5] <= 32'b0000000___00000___00101___000___00101___000_0011;
        end

    always @ (pc)
        begin
            instruction <= memfile[pc];
        end

endmodule

Khizar/verilog/singleImplem/instructionmemory_tb.v
`include "instructionmemory.v"

module instructionmemory_tb;

    reg [9:0] pc;
    
    wire [31:0] instruction;

    instructionmemory uut(pc, instruction);

    initial
        begin
            $dumpfile("./vcd/instructionmemory_tb.vcd");
            $dumpvars(1, instructionmemory_tb);

            #1
            pc = 0;

            #1
            $display("ins: %d", instruction);

            #1
            pc = 1;

            #1
            $display("ins: %d", instruction);

            #1
            pc = 2;

            #1
            $display("ins: %d", instruction);

            #1
            pc = 3;

            #1
            $display("ins: %d", instruction);

            #1
            pc = 4;

            #1
            $display("ins: %d", instruction);

            #1
            pc = 5;

            #1
            $display("ins: %d", instruction);

            #1
            pc = 6;

            #1
            $display("ins: %d", instruction);
        end

endmodule

Khizar/verilog/singleImplem/vcd/instructionmemory_tb.vcd
$date
	Sat Jul 15 16:42:44 2023
$end
$version
	Icarus Verilog
$end
$timescale
	1s
$end
$scope module instructionmemory_tb $end
$var wire 32 ! instruction [31:0] $end
$var reg 10 " pc [9:0] $end
$upscope $end
$enddefinitions $end
#0
$dumpvars
bx "
bx !
$end
#1
b1010111000000000101011100000000 !
b0 "
#3
b1110111000001000101011110000010 !
b1 "
#5
b1010111001010100101011100100000 !
b10 "
#7
b1010111001000000101011101100011 !
b11 "
#9
b1110111010001000111011110010010 !
b100 "
#11
b1010111001010110101011100101100 !
b101 "
#13
bx !
b110 "
